Workbook

Sheet Hadith
A1: No. | B1: Topic | C1: Hadith (English) | D1: Narrator | E1: Arabic text | F1: Reference | G1: In-book reference | H1: Grade | I1: Link (sunnah.com)
A2: 1 | B2: Patience in trials & hardship | C2: The Prophet (ﷺ) said, "Soon others will be preferred to you, and there will be things which you will not like." The companions of the Prophet (ﷺ) asked, "O Allah's Messenger (ﷺ)! What do you order us to do (in this case)? " He said, "(I order you) to give the rights that are on you and to ask your rights from Allah" | D2: Narrated Ibn Mas`ud | E2: حَدَّثَنَا مُحَمَّدُ بْنُ كَثِيرٍ، أَخْبَرَنَا سُفْيَانُ، عَنِ الأَعْمَشِ، عَنْ زَيْدِ بْنِ وَهْبٍ، عَنِ ابْنِ مَسْعُودٍ، عَنِ النَّبِيِّ صلى الله عليه وسلم قَالَ ‏"‏ سَتَكُونُ أَثَرَةٌ وَأُمُورٌ تُنْكِرُونَهَا ‏"‏‏.‏ قَالُوا يَا رَسُولَ اللَّهِ فَمَا تَأْمُرُنَا قَالَ ‏"‏ تُؤَدُّونَ الْحَقَّ الَّذِي عَلَيْكُمْ، وَتَسْأَلُونَ اللَّهَ الَّذِي لَكُمْ ‏"‏‏.‏ | F2: Sahih al-Bukhari 3603 | G2: Book 61, Hadith 110 | H2: Sahih | I2: https://sunnah.com/bukhari:3603
A3: 2 | B3: Patience in trials & hardship | C3: The Prophet (ﷺ) passed by a woman who was weeping beside a grave. He told her to fear Allah and be patient. She said to him, "Go away, for you have not been afflicted with a calamity like mine." And she did not recognize him. Then she was informed that he was the Prophet (ﷺ) . so she went to the house of the Prophet (ﷺ) and there she did not find any guard. Then she said to him, "I did not recognize you." He said, "Verily, the patience is at the first stroke of a calamity" | D3: Narrated Anas bin Malik | E3: حَدَّثَنَا آدَمُ، حَدَّثَنَا شُعْبَةُ، حَدَّثَنَا ثَابِتٌ، عَنْ أَنَسِ بْنِ مَالِكٍ ـ رضى الله عنه ـ قَالَ مَرَّ النَّبِيُّ صلى الله عليه وسلم بِامْرَأَةٍ تَبْكِي عِنْدَ قَبْرٍ فَقَالَ ‏"‏ اتَّقِي اللَّهَ وَاصْبِرِي ‏"‏‏.‏ قَالَتْ إِلَيْكَ عَنِّي، فَإِنَّكَ لَمْ تُصَبْ بِمُصِيبَتِي، وَلَمْ تَعْرِفْهُ‏.‏ فَقِيلَ لَهَا إِنَّهُ النَّبِيُّ صلى الله عليه وسلم‏.‏ فَأَتَتْ باب النَّبِيِّ صلى الله عليه وسلم فَلَمْ تَجِدْ عِنْدَهُ بَوَّابِينَ فَقَالَتْ لَمْ أَعْرِفْكَ‏.‏ فَقَالَ ‏"‏ إِنَّمَا الصَّبْرُ عِنْدَ الصَّدْمَةِ الأُولَى ‏"‏‏.‏ | F3: Sahih al-Bukhari 1283 | G3: Book 23, Hadith 43 | H3: Sahih | I3: https://sunnah.com/bukhari:1283
A4: 3 | B4: Patience in trials & hardship | C4: Allah's Messenger (ﷺ) said, "If Allah wants to do good to somebody, He afflicts him with trials" | D4: Narrated Abu Huraira | E4: حَدَّثَنَا عَبْدُ اللَّهِ بْنُ يُوسُفَ، أَخْبَرَنَا مَالِكٌ، عَنْ مُحَمَّدِ بْنِ عَبْدِ اللَّهِ بْنِ عَبْدِ الرَّحْمَنِ بْنِ أَبِي صَعْصَعَةَ، أَنَّهُ قَالَ سَمِعْتُ سَعِيدَ بْنَ يَسَارٍ أَبَا الْحُبَابِ، يَقُولُ سَمِعْتُ أَبَا هُرَيْرَةَ، يَقُولُ قَالَ رَسُولُ اللَّهِ صلى الله عليه وسلم ‏ "‏ مَنْ يُرِدِ اللَّهُ بِهِ خَيْرًا يُصِبْ مِنْهُ ‏"‏‏.‏ | F4: Sahih al-Bukhari 5645 | G4: Book 75, Hadith 5 | H4: Sahih | I4: https://sunnah.com/bukhari:5645
A5: 4 | B5: Patience in trials & hardship | C5: The Prophet (ﷺ) said, "None of you should wish for death because of a calamity befalling him; but if he has to wish for death, he should say: "O Allah! Keep me alive as long as life is better for me, and let me die if death is better for me. | D5: Narrated Anas bin Malik | E5: حَدَّثَنَا آدَمُ، حَدَّثَنَا شُعْبَةُ، حَدَّثَنَا ثَابِتٌ الْبُنَانِيُّ، عَنْ أَنَسِ بْنِ مَالِكٍ ـ رضى الله عنه ـ قَالَ النَّبِيُّ صلى الله عليه وسلم ‏ "‏ لاَ يَتَمَنَّيَنَّ أَحَدُكُمُ الْمَوْتَ مِنْ ضُرٍّ أَصَابَهُ، فَإِنْ كَانَ لاَ بُدَّ فَاعِلاً فَلْيَقُلِ اللَّهُمَّ أَحْيِنِي مَا كَانَتِ الْحَيَاةُ خَيْرًا لِي، وَتَوَفَّنِي إِذَا كَانَتِ الْوَفَاةُ خَيْرًا لِي ‏"‏‏.‏ | F5: Sahih al-Bukhari 5671 | G5: Book 75, Hadith 31 | H5: Sahih | I5: https://sunnah.com/bukhari:5671
A6: 5 | B6: Patience in trials & hardship | C6: Some Ansari persons asked for (something) from Allah's Messenger (ﷺ) and he gave them. They again asked him for (something) and he again gave them. And then they asked him and he gave them again till all that was with him finished. And then he said "If I had anything. I would not keep it away from you. (Remember) Whoever abstains from asking others, Allah will make him contented, and whoever tries to make himself self-sufficient, Allah will make him self-sufficient. And whoever remains patient, Allah will make him patient. Nobody can be given a blessing better and greater than patience" | D6: Narrated Abu Sa`id Al-Khudri | E6: حَدَّثَنَا عَبْدُ اللَّهِ بْنُ يُوسُفَ، أَخْبَرَنَا مَالِكٌ، عَنِ ابْنِ شِهَابٍ، عَنْ عَطَاءِ بْنِ يَزِيدَ اللَّيْثِيِّ، عَنْ أَبِي سَعِيدٍ الْخُدْرِيِّ ـ رضى الله عنه ـ أَنَّ نَاسًا مِنَ الأَنْصَارِ سَأَلُوا رَسُولَ اللَّهِ صلى الله عليه وسلم فَأَعْطَاهُمْ، ثُمَّ سَأَلُوهُ فَأَعْطَاهُمْ، حَتَّى نَفِدَ مَا عِنْدَهُ فَقَالَ ‏ "‏ مَا يَكُونُ عِنْدِي مِنْ خَيْرٍ فَلَنْ أَدَّخِرَهُ عَنْكُمْ، وَمَنْ يَسْتَعْفِفْ يُعِفَّهُ اللَّهُ، وَمَنْ يَسْتَغْنِ يُغْنِهِ اللَّهُ، وَمَنْ يَتَصَبَّرْ يُصَبِّرْهُ اللَّهُ، وَمَا أُعْطِيَ أَحَدٌ عَطَاءً خَيْرًا وَأَوْسَعَ مِنَ الصَّبْرِ ‏"‏‏.‏ | F6: Sahih al-Bukhari 1469 | G6: Book 24, Hadith 71 | H6: Sahih | I6: https://sunnah.com/bukhari:1469
A7: 6 | B7: Patience in trials & hardship | C7: Allah's Messenger (ﷺ) said, "The example of a believer is that of a fresh tender plant; from whatever direction the wind comes, it bends it, but when the wind becomes quiet, it becomes straight again. Similarly, a believer is afflicted with calamities (but he remains patient till Allah removes his difficulties.) And an impious wicked person is like a pine tree which keeps hard and straight till Allah cuts (breaks) it down when He wishes." (See Hadith No. 558, Vol) | D7: Narrated Abu Huraira | E7: حَدَّثَنَا إِبْرَاهِيمُ بْنُ الْمُنْذِرِ، قَالَ حَدَّثَنِي مُحَمَّدُ بْنُ فُلَيْحٍ، قَالَ حَدَّثَنِي أَبِي، عَنْ هِلاَلِ بْنِ عَلِيٍّ، مِنْ بَنِي عَامِرِ بْنِ لُؤَىٍّ عَنْ عَطَاءِ بْنِ يَسَارٍ، عَنْ أَبِي هُرَيْرَةَ ـ رضى الله عنه ـ قَالَ قَالَ رَسُولُ اللَّهِ صلى الله عليه وسلم ‏ "‏ مَثَلُ الْمُؤْمِنِ كَمَثَلِ الْخَامَةِ مِنَ الزَّرْعِ مِنْ حَيْثُ أَتَتْهَا الرِّيحُ كَفَأَتْهَا، فَإِذَا اعْتَدَلَتْ تَكَفَّأُ بِالْبَلاَءِ، وَالْفَاجِرُ كَالأَرْزَةِ صَمَّاءَ مُعْتَدِلَةً حَتَّى يَقْصِمَهَا اللَّهُ إِذَا شَاءَ ‏"‏‏.‏ | F7: Sahih al-Bukhari 5644 | G7: Book 75, Hadith 4 | H7: Sahih | I7: https://sunnah.com/bukhari:5644
A8: 7 | B8: Patience in trials & hardship | C8: Once the Prophet (ﷺ) distributed something (among his followers. A man said, "This distribution has not been done (with justice) seeking Allah's Countenance." I went to the Prophet (ﷺ) and told him (of that). He became so angry that I saw the signs of anger on his face. Then he said, "May Allah bestow His Mercy on Moses, for he was harmed more (in a worse manner) than this; yet he endured patiently" | D8: Narrated `Abdullah | E8: حَدَّثَنَا أَبُو الْوَلِيدِ، حَدَّثَنَا شُعْبَةُ، عَنِ الأَعْمَشِ، قَالَ سَمِعْتُ أَبَا وَائِلٍ، قَالَ سَمِعْتُ عَبْدَ اللَّهِ ـ رضى الله عنه ـ قَالَ قَسَمَ النَّبِيُّ صلى الله عليه وسلم قَسْمًا، فَقَالَ رَجُلٌ إِنَّ هَذِهِ لَقِسْمَةٌ مَا أُرِيدَ بِهَا وَجْهُ اللَّهِ‏.‏ فَأَتَيْتُ النَّبِيَّ صلى الله عليه وسلم فَأَخْبَرْتُهُ، فَغَضِبَ حَتَّى رَأَيْتُ الْغَضَبَ فِي وَجْهِهِ، ثُمَّ قَالَ ‏ "‏ يَرْحَمُ اللَّهُ مُوسَى قَدْ أُوذِيَ بِأَكْثَرَ مِنْ هَذَا فَصَبَرَ ‏"‏‏.‏ | F8: Sahih al-Bukhari 3405 | G8: Book 60, Hadith 78 | H8: Sahih | I8: https://sunnah.com/bukhari:3405
A9: 8 | B9: Patience in trials & hardship | C9: I heard Allah's Messenger (ﷺ) saying, "Allah said, 'If I deprive my slave of his two beloved things (i.e., his eyes) and he remains patient, I will let him enter Paradise in compensation for them" | D9: Narrated Anas bin Malik | E9: حَدَّثَنَا عَبْدُ اللَّهِ بْنُ يُوسُفَ، حَدَّثَنَا اللَّيْثُ، قَالَ حَدَّثَنِي ابْنُ الْهَادِ، عَنْ عَمْرٍو، مَوْلَى الْمُطَّلِبِ عَنْ أَنَسِ بْنِ مَالِكٍ ـ رضى الله عنه ـ قَالَ سَمِعْتُ النَّبِيَّ صلى الله عليه وسلم يَقُولُ ‏ "‏ إِنَّ اللَّهَ قَالَ إِذَا ابْتَلَيْتُ عَبْدِي بِحَبِيبَتَيْهِ فَصَبَرَ عَوَّضْتُهُ مِنْهُمَا الْجَنَّةَ ‏"‏‏.‏ يُرِيدُ عَيْنَيْهِ‏.‏ تَابَعَهُ أَشْعَثُ بْنُ جَابِرٍ وَأَبُو ظِلاَلٍ عَنْ أَنَسٍ عَنِ النَّبِيِّ صلى الله عليه وسلم‏.‏ | F9: Sahih al-Bukhari 5653 | G9: Book 75, Hadith 13 | H9: Sahih | I9: https://sunnah.com/bukhari:5653
A10: 9 | B10: Patience in trials & hardship | C10: Ibn `Abbas said to me, "Shall I show you a woman of the people of Paradise?" I said, "Yes." He said, "This black lady came to the Prophet (ﷺ) and said, 'I get attacks of epilepsy and my body becomes uncovered; please invoke Allah for me.' The Prophet (ﷺ) said (to her), 'If you wish, be patient and you will have (enter) Paradise; and if you wish, I will invoke Allah to cure you.' She said, 'I will remain patient,' and added, 'but I become uncovered, so please invoke Allah for me that I may not become uncovered.' So he invoked Allah for her." Narrated 'Ata: That he had seen Um Zafar, the tall black lady, at (holding) the curtain of the Ka`ba. | D10: Narrated 'Ata bin Abi Rabah | E10: حَدَّثَنَا مُسَدَّدٌ، حَدَّثَنَا يَحْيَى، عَنْ عِمْرَانَ أَبِي بَكْرٍ، قَالَ حَدَّثَنِي عَطَاءُ بْنُ أَبِي رَبَاحٍ، قَالَ قَالَ لِي ابْنُ عَبَّاسٍ أَلاَ أُرِيكَ امْرَأَةً مِنْ أَهْلِ الْجَنَّةِ قُلْتُ بَلَى‏.‏ قَالَ هَذِهِ الْمَرْأَةُ السَّوْدَاءُ أَتَتِ النَّبِيَّ صلى الله عليه وسلم فَقَالَتْ إِنِّي أُصْرَعُ، وَإِنِّي أَتَكَشَّفُ فَادْعُ اللَّهَ لِي‏.‏ قَالَ ‏ "‏ إِنْ شِئْتِ صَبَرْتِ وَلَكِ الْجَنَّةُ وَإِنْ شِئْتِ دَعَوْتُ اللَّهَ أَنْ يُعَافِيَكِ ‏"‏‏.‏ فَقَالَتْ أَصْبِرُ‏.‏ فَقَالَتْ إِنِّي أَتَكَشَّفُ فَادْعُ اللَّهَ أَنْ لاَ أَتَكَشَّفَ، فَدَعَا لَهَا‏.‏ حَدَّثَنَا مُحَمَّدٌ، أَخْبَرَنَا مَخْلَدٌ، عَنِ ابْنِ جُرَيْجٍ، أَخْبَرَنِي عَطَاءٌ، أَنَّهُ رَأَى أُمَّ زُفَرَ تِلْكَ، امْرَأَةٌ طَوِيلَةٌ سَوْدَاءُ عَلَى سِتْرِ الْكَعْبَةِ‏.‏ | F10: Sahih al-Bukhari 5652 | G10: Book 75, Hadith 12 | H10: Sahih | I10: https://sunnah.com/bukhari:5652
A11: 10 | B11: Patience in trials & hardship | C11: Narrated Sa`d bin Ubaid:(the Maula of `Abdur-Rahman bin Azhar) Allah's Messenger (ﷺ) said, "None of you should long for death, for if he is a good man, he may increase his good deeds, and if he is an evil-doer, he may stop the evil deeds and repent" | E11: حَدَّثَنَا عَبْدُ اللَّهِ بْنُ مُحَمَّدٍ، حَدَّثَنَا هِشَامُ بْنُ يُوسُفَ، أَخْبَرَنَا مَعْمَرٌ، عَنِ الزُّهْرِيِّ، عَنْ أَبِي عُبَيْدٍ ـ اسْمُهُ سَعْدُ بْنُ عُبَيْدٍ مَوْلَى عَبْدِ الرَّحْمَنِ بْنِ أَزْهَرَ ـ عَنْ أَبِي هُرَيْرَةَ ـ أَنَّ رَسُولَ اللَّهِ صلى الله عليه وسلم قَالَ ‏ "‏ لاَ يَتَمَنَّى أَحَدُكُمُ الْمَوْتَ إِمَّا مُحْسِنًا فَلَعَلَّهُ يَزْدَادُ، وَإِمَّا مُسِيئًا فَلَعَلَّهُ يَسْتَعْتِبُ ‏"‏‏.‏ | F11: Sahih al-Bukhari 7235 | G11: Book 94, Hadith 10 | H11: Sahih | I11: https://sunnah.com/bukhari:7235
A12: 11 | B12: Patience in trials & hardship | C12: Allah's Messenger (ﷺ) said, "Allah gives respite to the oppressor, but when He takes him over, He never releases him." Then he recited:-- "Such is the seizure of your Lord when He seizes (population of) towns in the midst of their wrong: Painful indeed, and severe is His seizure" | D12: Narrated Abu Musa | E12: حَدَّثَنَا صَدَقَةُ بْنُ الْفَضْلِ، أَخْبَرَنَا أَبُو مُعَاوِيَةَ، حَدَّثَنَا بُرَيْدُ بْنُ أَبِي بُرْدَةَ، عَنْ أَبِي بُرْدَةَ، عَنْ أَبِي مُوسَى ـ رضى الله عنه ـ قَالَ قَالَ رَسُولُ اللَّهِ صلى الله عليه وسلم ‏ "‏ إِنَّ اللَّهَ لَيُمْلِي لِلظَّالِمِ حَتَّى إِذَا أَخَذَهُ لَمْ يُفْلِتْهُ ‏"‏‏.‏ قَالَ ثُمَّ قَرَأَ ‏{‏وَكَذَلِكَ أَخْذُ رَبِّكَ إِذَا أَخَذَ الْقُرَى وَهْىَ ظَالِمَةٌ إِنَّ أَخْذَهُ أَلِيمٌ شَدِيدٌ‏}‏ | F12: Sahih al-Bukhari 4686 | G12: Book 65, Hadith 208 | H12: Sahih | I12: https://sunnah.com/bukhari:4686
A13: 12 | B13: Patience in trials & hardship | C13: Strange are the ways of a believer for there is good in every affair of his and this is not the case with anyone else except in the case of a believer for if he has an occasion to feel delight, he thanks (God), thus there is a good for him in it, and if he gets into trouble and shows resignation (and endures it patiently), there is a good for him in it. | D13: Suhaib reported that Allah's Messenger (ﷺ) said | E13: حَدَّثَنَا هَدَّابُ بْنُ خَالِدٍ الأَزْدِيُّ، وَشَيْبَانُ بْنُ فَرُّوخَ، جَمِيعًا عَنْ سُلَيْمَانَ بْنِ الْمُغِيرَةِ، - وَاللَّفْظُ لِشَيْبَانَ - حَدَّثَنَا سُلَيْمَانُ، حَدَّثَنَا ثَابِتٌ، عَنْ عَبْدِ الرَّحْمَنِ بْنِ أَبِي لَيْلَى، عَنْ صُهَيْبٍ، قَالَ قَالَ رَسُولُ اللَّهِ صلى الله عليه وسلم ‏ "‏ عَجَبًا لأَمْرِ الْمُؤْمِنِ إِنَّ أَمْرَهُ كُلَّهُ خَيْرٌ وَلَيْسَ ذَاكَ لأَحَدٍ إِلاَّ لِلْمُؤْمِنِ إِنْ أَصَابَتْهُ سَرَّاءُ شَكَرَ فَكَانَ خَيْرًا لَهُ وَإِنْ أَصَابَتْهُ ضَرَّاءُ صَبَرَ فَكَانَ خَيْرًا لَهُ ‏"‏ ‏.‏ | F13: Sahih Muslim 2999 | G13: Book 55, Hadith 82 | H13: Sahih | I13: https://sunnah.com/muslim:2999
A14: 13 | B14: Patience in trials & hardship | C14: O Messenger of Allah(s.a.w)! Which of the people is tried most severely?" He said: "The Prophets, then those nearest to them, then those nearest to them. A man is tried according to his religion; if he is firm in his religion, then his trials are more severe, and if he is frail in his religion, then he is tried according to the strength of his religion. The servant shall continue to be tried until he is left walking upon the earth without any sins. | D14: Mus'ab bin Sa'd narrated from his father that a man said | E14: حَدَّثَنَا قُتَيْبَةُ، حَدَّثَنَا حَمَّادُ بْنُ زَيْدٍ، عَنْ عَاصِمِ بْنِ بَهْدَلَةَ، عَنْ مُصْعَبِ بْنِ سَعْدٍ، عَنْ أَبِيهِ، قَالَ قُلْتُ يَا رَسُولَ اللَّهِ أَىُّ النَّاسِ أَشَدُّ بَلاَءً قَالَ ‏ "‏ الأَنْبِيَاءُ ثُمَّ الأَمْثَلُ فَالأَمْثَلُ فَيُبْتَلَى الرَّجُلُ عَلَى حَسَبِ دِينِهِ فَإِنْ كَانَ دِينُهُ صُلْبًا اشْتَدَّ بَلاَؤُهُ وَإِنْ كَانَ فِي دِينِهِ رِقَّةٌ ابْتُلِيَ عَلَى حَسَبِ دِينِهِ فَمَا يَبْرَحُ الْبَلاَءُ بِالْعَبْدِ حَتَّى يَتْرُكَهُ يَمْشِي عَلَى الأَرْضِ مَا عَلَيْهِ خَطِيئَةٌ ‏"‏ ‏.‏ قَالَ أَبُو عِيسَى هَذَا حَدِيثٌ حَسَنٌ صَحِيحٌ ‏.‏ وَفِي الْبَابِ عَنْ أَبِي هُرَيْرَةَ وَأُخْتِ حُذَيْفَةَ بْنِ الْيَمَانِ ‏أَنَّ النَّبِيَّ صَلَّى اللَّهُ عَلَيْهِ وَسَلَّمَ سُئِلَ أَيُّ النَّاسِ أَشَدُّ بَلَاءً قَالَ الْأَنْبِيَاءُ ثُمَّ الْأَمْثَلُ فَالْأَمْثَلُ | F14: Jami' at-Tirmidhi 2398 | G14: Book 36, Hadith 96 | H14: Hasan Sahih (Al-Albani) | I14: https://sunnah.com/tirmidhi:2398
A15: 14 | B15: Patience in trials & hardship | C15: The Messenger of Allah sent Mu'adh [bin Jabal] to Yemen, and said: 'Beware of the supplication of the oppressed; for indeed there is no barrier between it and Allah. | D15: Ibn 'Abbas narrated | E15: حَدَّثَنَا أَبُو كُرَيْبٍ، حَدَّثَنَا وَكِيعٌ، عَنْ زَكَرِيَّا بْنِ إِسْحَاقَ، عَنْ يَحْيَى بْنِ عَبْدِ اللَّهِ بْنِ صَيْفِيٍّ، عَنْ أَبِي مَعْبَدٍ، عَنِ ابْنِ عَبَّاسٍ، أَنَّ رَسُولَ اللَّهِ صلى الله عليه وسلم بَعَثَ مُعَاذَ بْنَ جَبَلٍ إِلَى الْيَمَنِ فَقَالَ ‏ "‏ اتَّقِ دَعْوَةَ الْمَظْلُومِ فَإِنَّهَا لَيْسَ بَيْنَهَا وَبَيْنَ اللَّهِ حِجَابٌ ‏"‏ ‏.‏ قَالَ أَبُو عِيسَى وَفِي الْبَابِ عَنْ أَنَسٍ وَأَبِي هُرَيْرَةَ وَعَبْدِ اللَّهِ بْنِ عُمَرَ وَأَبِي سَعِيدٍ ‏.‏ وَهَذَا حَدِيثٌ حَسَنٌ صَحِيحٌ وَأَبُو مَعْبَدٍ اسْمُهُ نَافِذٌ ‏.‏ | F15: Jami' at-Tirmidhi 2014 | G15: Book 27, Hadith 120 | H15: Sahih (Al-Albani) | I15: https://sunnah.com/tirmidhi:2014
A16: 15 | B16: Patience in trials & hardship | C16: “The believer who mixes with people and bears their annoyance with patience will have a greater reward than the believer who does not mix with people and does not put up with their annoyance.” | D16: It was narrated from Ibn ‘Umar that the Messenger of Allah (ﷺ) said | E16: حَدَّثَنَا عَلِيُّ بْنُ مَيْمُونٍ الرَّقِّيُّ، حَدَّثَنَا عَبْدُ الْوَاحِدِ بْنُ صَالِحٍ، حَدَّثَنَا إِسْحَاقُ بْنُ يُوسُفَ، عَنِ الأَعْمَشِ، عَنْ يَحْيَى بْنِ وَثَّابٍ، عَنِ ابْنِ عُمَرَ، قَالَ قَالَ رَسُولُ اللَّهِ ـ صلى الله عليه وسلم ـ ‏ "‏ الْمُؤْمِنُ الَّذِي يُخَالِطُ النَّاسَ وَيَصْبِرُ عَلَى أَذَاهُمْ أَعْظَمُ أَجْرًا مِنَ الْمُؤْمِنِ الَّذِي لاَ يُخَالِطُ النَّاسَ وَلاَ يَصْبِرُ عَلَى أَذَاهُمْ ‏"‏ ‏.‏ | F16: Sunan Ibn Majah 4032 | G16: Book 36, Hadith 107 | H16: Sahih (Al-Albani) | I16: https://sunnah.com/ibnmajah:4032
A17: 16 | B17: Patience in trials & hardship | C17: We complained to the Messenger of Allah [SAW] when he was reclining on his rolled-up Burdah in the shade of the Ka'bah. We said: 'Will you not pray for victory for us, will you not pray to Allah for us? | D17: It was narrated that Khabbab bin Al-Aratt said | E17: أَخْبَرَنَا يَعْقُوبُ بْنُ إِبْرَاهِيمَ، وَمُحَمَّدُ بْنُ الْمُثَنَّى، عَنْ يَحْيَى، عَنْ إِسْمَاعِيلَ، قَالَ حَدَّثَنَا قَيْسٌ، عَنْ خَبَّابِ بْنِ الأَرَتِّ، قَالَ شَكَوْنَا إِلَى رَسُولِ اللَّهِ صلى الله عليه وسلم وَهُوَ مُتَوَسِّدٌ بُرْدَةً لَهُ فِي ظِلِّ الْكَعْبَةِ فَقُلْنَا أَلاَ تَسْتَنْصِرُ لَنَا أَلاَ تَدْعُو اللَّهَ لَنَا | F17: Sunan an-Nasa'i 5320 | G17: Book 48, Hadith 281 | H17: Sahih (Al-Albani) | I17: https://sunnah.com/nasai:5320
A18: 17 | B18: Illness & pain | C18: The Prophet (ﷺ) used to say to the patient, "In the Name of Allah The earth of our land and the saliva of some of us cure our patient" | D18: Narrated `Aisha | E18: حَدَّثَنَا عَلِيُّ بْنُ عَبْدِ اللَّهِ، حَدَّثَنَا سُفْيَانُ، قَالَ حَدَّثَنِي عَبْدُ رَبِّهِ بْنُ سَعِيدٍ، عَنْ عَمْرَةَ، عَنْ عَائِشَةَ ـ رضى الله عنها ـ أَنَّ النَّبِيَّ صلى الله عليه وسلم كَانَ يَقُولُ لِلْمَرِيضِ ‏ "‏ بِسْمِ اللَّهِ، تُرْبَةُ أَرْضِنَا‏.‏ بِرِيقَةِ بَعْضِنَا، يُشْفَى سَقِيمُنَا بِإِذْنِ رَبِّنَا ‏"‏‏.‏ | F18: Sahih al-Bukhari 5745 | G18: Book 76, Hadith 60 | H18: Sahih | I18: https://sunnah.com/bukhari:5745
A19: 18 | B19: Illness & pain | C19: Narrated `Aisha:(the wife of the Prophet) I asked Allah's Messenger (ﷺ) about the plague. He told me that it was a Punishment sent by Allah on whom He wished, and Allah made it a source of mercy for the believers, for if one in the time of an epidemic plague stays in his country patiently hoping for Allah's Reward and believing that nothing will befall him except what Allah has written for him, he will get the reward of a martyr. | E19: حَدَّثَنَا مُوسَى بْنُ إِسْمَاعِيلَ، حَدَّثَنَا دَاوُدُ بْنُ أَبِي الْفُرَاتِ، حَدَّثَنَا عَبْدُ اللَّهِ بْنُ بُرَيْدَةَ، عَنْ يَحْيَى بْنِ يَعْمَرَ، عَنْ عَائِشَةَ ـ رضى الله عنها ـ زَوْجِ النَّبِيِّ صلى الله عليه وسلم قَالَتْ سَأَلْتُ رَسُولَ اللَّهِ صلى الله عليه وسلم عَنِ الطَّاعُونِ، فَأَخْبَرَنِي ‏ "‏ أَنَّهُ عَذَابٌ يَبْعَثُهُ اللَّهُ عَلَى مَنْ يَشَاءُ، وَأَنَّ اللَّهَ جَعَلَهُ رَحْمَةً لِلْمُؤْمِنِينَ، لَيْسَ مِنْ أَحَدٍ يَقَعُ الطَّاعُونُ فَيَمْكُثُ فِي بَلَدِهِ صَابِرًا مُحْتَسِبًا، يَعْلَمُ أَنَّهُ لاَ يُصِيبُهُ إِلاَّ مَا كَتَبَ اللَّهُ لَهُ، إِلاَّ كَانَ لَهُ مِثْلُ أَجْرِ شَهِيدٍ ‏"‏‏.‏ | F19: Sahih al-Bukhari 3474 | G19: Book 60, Hadith 141 | H19: Sahih | I19: https://sunnah.com/bukhari:3474
A20: 19 | B20: Illness & pain | C20: I visited Allah's Messenger (ﷺ) while he was suffering from a high fever. I said, "O Allah's Messenger (ﷺ)! You have a high fever." He said, "Yes, I have as much fever as two men of you." I said, "Is it because you will have a double reward?" He said, "Yes, it is so. No Muslim is afflicted with any harm, even if it were the prick of a thorn, but that Allah expiates his sins because of that, as a tree sheds its leaves" | D20: Narrated `Abdullah | E20: حَدَّثَنَا عَبْدَانُ، عَنْ أَبِي حَمْزَةَ، عَنِ الأَعْمَشِ، عَنْ إِبْرَاهِيمَ التَّيْمِيِّ، عَنِ الْحَارِثِ بْنِ سُوَيْدٍ، عَنْ عَبْدِ اللَّهِ، قَالَ دَخَلْتُ عَلَى رَسُولِ اللَّهِ صلى الله عليه وسلم وَهْوَ يُوعَكُ فَقُلْتُ يَا رَسُولَ اللَّهِ إِنَّكَ تُوعَكُ وَعْكًا شَدِيدًا‏.‏ قَالَ ‏"‏ أَجَلْ إِنِّي أُوعَكُ كَمَا يُوعَكُ رَجُلاَنِ مِنْكُمْ ‏"‏‏.‏ قُلْتُ ذَلِكَ أَنَّ لَكَ أَجْرَيْنِ قَالَ ‏"‏ أَجَلْ ذَلِكَ كَذَلِكَ، مَا مِنْ مُسْلِمٍ يُصِيبُهُ أَذًى شَوْكَةٌ فَمَا فَوْقَهَا، إِلاَّ كَفَّرَ اللَّهُ بِهَا سَيِّئَاتِهِ، كَمَا تَحُطُّ الشَّجَرَةُ وَرَقَهَا ‏"‏‏.‏ | F20: Sahih al-Bukhari 5648 | G20: Book 75, Hadith 8 | H20: Sahih | I20: https://sunnah.com/bukhari:5648
A21: 20 | B21: Illness & pain | C21: The Prophet (ﷺ) said, "No fatigue, nor disease, nor sorrow, nor sadness, nor hurt, nor distress befalls a Muslim, even if it were the prick he receives from a thorn, but that Allah expiates some of his sins for that" | D21: Narrated Abu Sa`id Al-Khudri and Abu Huraira | E21: حَدَّثَنِي عَبْدُ اللَّهِ بْنُ مُحَمَّدٍ، حَدَّثَنَا عَبْدُ الْمَلِكِ بْنُ عَمْرٍو، حَدَّثَنَا زُهَيْرُ بْنُ مُحَمَّدٍ، عَنْ مُحَمَّدِ بْنِ عَمْرِو بْنِ حَلْحَلَةَ، عَنْ عَطَاءِ بْنِ يَسَارٍ، عَنْ أَبِي سَعِيدٍ الْخُدْرِيِّ، وَعَنْ أَبِي هُرَيْرَةَ، عَنِ النَّبِيِّ صلى الله عليه وسلم قَالَ ‏ "‏ مَا يُصِيبُ الْمُسْلِمَ مِنْ نَصَبٍ وَلاَ وَصَبٍ وَلاَ هَمٍّ وَلاَ حُزْنٍ وَلاَ أَذًى وَلاَ غَمٍّ حَتَّى الشَّوْكَةِ يُشَاكُهَا، إِلاَّ كَفَّرَ اللَّهُ بِهَا مِنْ خَطَايَاهُ ‏"‏‏.‏ | F21: Sahih al-Bukhari 5641 | H21: Sahih | I21: https://sunnah.com/bukhari:5641
A22: 21 | B22: Illness & pain | C22: Thabit and I went to Anas bin Malik. Thabit said, "O Abu Hamza! I am sick." On that Anas said, "Shall I treat you with the Ruqya of Allah's Messenger (ﷺ)?" Thabit said, "Yes," Anas recited, "O Allah! The Lord of the people, the Remover of trouble! (Please) cure (Heal) (this patient), for You are the Healer. None brings about healing but You; a healing that will leave behind no ailment" | D22: Narrated `Abdul `Aziz | E22: حَدَّثَنَا مُسَدَّدٌ، حَدَّثَنَا عَبْدُ الْوَارِثِ، عَنْ عَبْدِ الْعَزِيزِ، قَالَ دَخَلْتُ أَنَا وَثَابِتٌ، عَلَى أَنَسِ بْنِ مَالِكٍ فَقَالَ ثَابِتٌ يَا أَبَا حَمْزَةَ اشْتَكَيْتُ‏.‏ فَقَالَ أَنَسٌ أَلاَ أَرْقِيكَ بِرُقْيَةِ رَسُولِ اللَّهِ صلى الله عليه وسلم قَالَ بَلَى‏.‏ قَالَ ‏ "‏ اللَّهُمَّ رَبَّ النَّاسِ مُذْهِبَ الْبَاسِ اشْفِ أَنْتَ الشَّافِي لاَ شَافِيَ إِلاَّ أَنْتَ، شِفَاءً لاَ يُغَادِرُ سَقَمًا ‏"‏‏.‏ | F22: Sahih al-Bukhari 5742 | G22: Book 76, Hadith 57 | H22: Sahih | I22: https://sunnah.com/bukhari:5742
A23: 22 | B23: Illness & pain | C23: I visited the Prophet (ﷺ) during his illness and touched him while he was having a fever. I said to him, "You have a high fever; is it because you will get a double reward?" He said, "Yes. No Muslim is afflicted with any harm, but that his sins will be annulled as the leave of a tree fall down" | D23: Narrated `Abdullah | E23: حَدَّثَنَا قَبِيصَةُ، حَدَّثَنَا سُفْيَانُ، عَنِ الأَعْمَشِ، عَنْ إِبْرَاهِيمَ التَّيْمِيِّ، عَنِ الْحَارِثِ بْنِ سُوَيْدٍ، عَنْ عَبْدِ اللَّهِ ـ رضى الله عنه ـ قَالَ أَتَيْتُ النَّبِيَّ صلى الله عليه وسلم فِي مَرَضِهِ فَمَسِسْتُهُ وَهْوَ يُوعَكُ وَعْكًا شَدِيدًا فَقُلْتُ إِنَّكَ لَتُوعَكُ وَعْكًا شَدِيدًا، وَذَلِكَ أَنَّ لَكَ أَجْرَيْنِ‏.‏ قَالَ ‏ "‏ أَجَلْ، وَمَا مِنْ مُسْلِمٍ يُصِيبُهُ أَذًى إِلاَّ حَاتَّتْ عَنْهُ خَطَايَاهُ كَمَا تَحَاتُّ وَرَقُ الشَّجَرِ ‏"‏‏.‏ | F23: Sahih al-Bukhari 5661 | G23: Book 75, Hadith 21 | H23: Sahih | I23: https://sunnah.com/bukhari:5661
A24: 23 | B24: Illness & pain | C24: The Prophet (ﷺ) said, "There is no disease that Allah has created, except that He also has created its treatment" | D24: Narrated Abu Huraira | E24: حَدَّثَنَا مُحَمَّدُ بْنُ الْمُثَنَّى، حَدَّثَنَا أَبُو أَحْمَدَ الزُّبَيْرِيُّ، حَدَّثَنَا عُمَرُ بْنُ سَعِيدِ بْنِ أَبِي حُسَيْنٍ، قَالَ حَدَّثَنِي عَطَاءُ بْنُ أَبِي رَبَاحٍ، عَنْ أَبِي هُرَيْرَةَ ـ رضى الله عنه ـ عَنِ النَّبِيِّ صلى الله عليه وسلم قَالَ ‏ "‏ مَا أَنْزَلَ اللَّهُ دَاءً إِلاَّ أَنْزَلَ لَهُ شِفَاءً ‏"‏‏.‏ | F24: Sahih al-Bukhari 5678 | G24: Book 76, Hadith 1 | H24: Sahih | I24: https://sunnah.com/bukhari:5678
A25: 24 | B25: Illness & pain | C25: Whenever Allah's Messenger (ﷺ) paid a visit to a patient, or a patient was brought to him, he used to invoke Allah, saying, "Take away the disease, O the Lord of the people! Cure him as You are the One Who cures. There is no cure but Yours, a cure that leaves no disease" | D25: Narrated `Aisha | E25: حَدَّثَنَا مُوسَى بْنُ إِسْمَاعِيلَ، حَدَّثَنَا أَبُو عَوَانَةَ، عَنْ مَنْصُورٍ، عَنْ إِبْرَاهِيمَ، عَنْ مَسْرُوقٍ، عَنْ عَائِشَةَ ـ رضى الله عنها أَنَّ رَسُولَ اللَّهِ صلى الله عليه وسلم كَانَ إِذَا أَتَى مَرِيضًا ـ أَوْ أُتِيَ بِهِ ـ قَالَ ‏ "‏ أَذْهِبِ الْبَاسَ رَبَّ النَّاسِ، اشْفِ وَأَنْتَ الشَّافِي لاَ شِفَاءَ إِلاَّ شِفَاؤُكَ، شِفَاءً لاَ يُغَادِرُ سَقَمًا ‏"‏‏.‏ قَالَ عَمْرُو بْنُ أَبِي قَيْسٍ وَإِبْرَاهِيمُ بْنُ طَهْمَانَ عَنْ مَنْصُورٍ عَنْ إِبْرَاهِيمَ وَأَبِي الضُّحَى إِذَا أُتِيَ بِالْمَرِيضِ، وَقَالَ جَرِيرٌ عَنْ مَنْصُورٍ عَنْ أَبِي الضُّحَى وَحْدَهُ، وَقَالَ إِذَا أَتَى مَرِيضًا‏.‏ | F25: Sahih al-Bukhari 5675 | G25: Book 75, Hadith 35 | H25: Sahih | I25: https://sunnah.com/bukhari:5675
A26: 25 | B26: Illness & pain | C26: Whenever Allah's Messenger (ﷺ) became sick, he would recite Mu'awwidhat (Surat Al-Falaq and Surat An- Nas) and then blow his breath over his body. When he became seriously ill, I used to recite (these two Suras) and rub his hands over his body hoping for its blessings. | D26: Narrated `Aisha | E26: حَدَّثَنَا عَبْدُ اللَّهِ بْنُ يُوسُفَ، أَخْبَرَنَا مَالِكٌ، عَنِ ابْنِ شِهَابٍ، عَنْ عُرْوَةَ، عَنْ عَائِشَةَ، رضى الله عنها أَنَّ رَسُولَ اللَّهِ صلى الله عليه وسلم كَانَ إِذَا اشْتَكَى يَقْرَأُ عَلَى نَفْسِهِ بِالْمُعَوِّذَاتِ وَيَنْفُثُ، فَلَمَّا اشْتَدَّ وَجَعُهُ كُنْتُ أَقْرَأُ عَلَيْهِ وَأَمْسَحُ بِيَدِهِ رَجَاءَ بَرَكَتِهَا‏.‏ | F26: Sahih al-Bukhari 5016 | G26: Book 66, Hadith 38 | H26: Sahih | I26: https://sunnah.com/bukhari:5016
A27: 26 | B27: Illness & pain | C27: Allah's Messenger (ﷺ) entered upon a sick bedouin in whom he went to visit and said to him, "Don't worry, Tahur (i.e., your illness will be a means of cleansing of your sins), if Allah Will." The bedouin said, "Tahur! No, but it is a fever that is burning in the body of an old man and it will make him visit his grave." The Prophet (ﷺ) said, "Then it is so" | D27: Narrated Ibn `Abbas | E27: حَدَّثَنَا مُحَمَّدٌ، حَدَّثَنَا عَبْدُ الْوَهَّابِ الثَّقَفِيُّ، حَدَّثَنَا خَالِدٌ الْحَذَّاءُ، عَنْ عِكْرِمَةَ، عَنِ ابْنِ عَبَّاسٍ ـ رضى الله عنهما ـ أَنَّ رَسُولَ اللَّهِ صلى الله عليه وسلم دَخَلَ عَلَى أَعْرَابِيٍّ يَعُودُهُ فَقَالَ ‏"‏ لاَ بَأْسَ عَلَيْكَ طَهُورٌ، إِنْ شَاءَ اللَّهُ ‏"‏‏.‏ قَالَ قَالَ الأَعْرَابِيُّ طَهُورٌ، بَلْ هِيَ حُمَّى تَفُورُ عَلَى شَيْخٍ كَبِيرٍ، تُزِيرُهُ الْقُبُورَ‏.‏ قَالَ النَّبِيُّ صلى الله عليه وسلم ‏"‏ فَنَعَمْ إِذًا ‏"‏‏.‏ | F27: Sahih al-Bukhari 7470 | G27: Book 97, Hadith 96 | H27: Sahih | I27: https://sunnah.com/bukhari:7470
A28: 27 | B28: Illness & pain | C28: I heard Abu Burda who accompanied Yazid bin Abi Kabsha on a journey. Yazid used to observe fasting on journeys. Abu Burda said to him, "I heard Abu Musa several times saying that Allah's Apostle said, 'When a slave falls ill or travels, then he will get reward similar to that he gets for good deeds practiced at home when in good health" | D28: Narrated Ibrahim Abu Isma`il As-Saksaki | E28: حَدَّثَنَا مَطَرُ بْنُ الْفَضْلِ، حَدَّثَنَا يَزِيدُ بْنُ هَارُونَ، حَدَّثَنَا الْعَوَّامُ، حَدَّثَنَا إِبْرَاهِيمُ أَبُو إِسْمَاعِيلَ السَّكْسَكِيُّ، قَالَ سَمِعْتُ أَبَا بُرْدَةَ، وَاصْطَحَبَ، هُوَ وَيَزِيدُ بْنُ أَبِي كَبْشَةَ فِي سَفَرٍ، فَكَانَ يَزِيدُ يَصُومُ فِي السَّفَرِ فَقَالَ لَهُ أَبُو بُرْدَةَ سَمِعْتُ أَبَا مُوسَى مِرَارًا يَقُولُ قَالَ رَسُولُ اللَّهِ صلى الله عليه وسلم ‏ "‏ إِذَا مَرِضَ الْعَبْدُ أَوْ سَافَرَ، كُتِبَ لَهُ مِثْلُ مَا كَانَ يَعْمَلُ مُقِيمًا صَحِيحًا ‏"‏‏.‏ | F28: Sahih al-Bukhari 2996 | G28: Book 56, Hadith 205 | H28: Sahih | I28: https://sunnah.com/bukhari:2996
A29: 28 | B29: Illness & pain | C29: Verily, when a Muslim visits his brother in Islam he is supposed to remain in the fruit garden of Paradise until he returns. | D29: Thauban reported Allah's Apostle (ﷺ) as saying | E29: حَدَّثَنَا يَحْيَى بْنُ حَبِيبٍ الْحَارِثِيُّ، حَدَّثَنَا يَزِيدُ بْنُ زُرَيْعٍ، حَدَّثَنَا خَالِدٌ، عَنْ أَبِي قِلاَبَةَ، عَنْ أَبِي أَسْمَاءَ الرَّحَبِيِّ، عَنْ ثَوْبَانَ، عَنِ النَّبِيِّ صلى الله عليه وسلم قَالَ ‏ "‏ إِنَّ الْمُسْلِمَ إِذَا عَادَ أَخَاهُ الْمُسْلِمَ لَمْ يَزَلْ فِي خُرْفَةِ الْجَنَّةِ حَتَّى يَرْجِعَ ‏"‏ ‏.‏ | F29: Sahih Muslim 2568c | G29: Book 45, Hadith 51 | H29: Sahih | I29: https://sunnah.com/muslim:2568c
A30: 29 | B30: Illness & pain | C30: Jabir b. Abdullah reported that Allah's Messenger (ﷺ) visited Umm Sa'ib or Umm Musayyib and said:Umm Sa'ib or Umm Musayyib. why is it that you are shivering? She said:" It is fever and may it not be blessed by Allah, whereupon he (the Holy Prophet) said: Don't curse fever for it expiates the sin of the children of Adam just as furnace removes the alloy of iron" | E30: حَدَّثَنِي عُبَيْدُ اللَّهِ بْنُ عُمَرَ الْقَوَارِيرِيُّ، حَدَّثَنَا يَزِيدُ بْنُ زُرَيْعٍ، حَدَّثَنَا الْحَجَّاجُ الصَّوَّافُ، حَدَّثَنِي أَبُو الزُّبَيْرِ، حَدَّثَنَا جَابِرُ بْنُ عَبْدِ اللَّهِ، أَنَّ رَسُولَ اللَّهِ صلى الله عليه وسلم دَخَلَ عَلَى أُمِّ السَّائِبِ أَوْ أُمِّ الْمُسَيَّبِ فَقَالَ ‏"‏ مَا لَكِ يَا أُمَّ السَّائِبِ أَوْ يَا أُمَّ الْمُسَيَّبِ تُزَفْزِفِينَ ‏"‏ ‏.‏ قَالَتِ الْحُمَّى لاَ بَارَكَ اللَّهُ فِيهَا ‏.‏ فَقَالَ ‏"‏ لاَ تَسُبِّي الْحُمَّى فَإِنَّهَا تُذْهِبُ خَطَايَا بَنِي آدَمَ كَمَا يُذْهِبُ الْكِيرُ خَبَثَ الْحَدِيدِ ‏"‏ ‏.‏ | F30: Sahih Muslim 2575 | G30: Book 45, Hadith 68 | H30: Sahih | I30: https://sunnah.com/muslim:2575
A31: 30 | B31: Illness & pain | C31: Uthman b. Abu al-'As Al-Thaqafi reported that he made a complaint of pain to Allah's Messenger (ﷺ) that he felt in his body at the time he had become Muslim. Thereupon Allah's Messenger (ﷺ) said:Place your hand at the place where you feel pain in your body and say Bismillah (in the name of Allah) three times and seven times A'udhu billahi wa qudratihi min sharri ma ajidu wa uhadhiru (I seek refuge with Allah and with His Power from the evil that I find and that I fear) | E31: حَدَّثَنِي أَبُو الطَّاهِرِ، وَحَرْمَلَةُ بْنُ يَحْيَى، قَالاَ أَخْبَرَنَا ابْنُ وَهْبٍ، أَخْبَرَنِي يُونُسُ، عَنِ ابْنِ شِهَابٍ، أَخْبَرَنِي نَافِعُ بْنُ جُبَيْرِ بْنِ مُطْعِمٍ، عَنْ عُثْمَانَ بْنِ أَبِي الْعَاصِ الثَّقَفِيِّ، أَنَّهُ شَكَا إِلَى رَسُولِ اللَّهِ صلى الله عليه وسلم وَجَعًا يَجِدُهُ فِي جَسَدِهِ مُنْذُ أَسْلَمَ ‏.‏ فَقَالَ لَهُ رَسُولُ اللَّهِ صلى الله عليه وسلم ‏ "‏ ضَعْ يَدَكَ عَلَى الَّذِي تَأَلَّمَ مِنْ جَسَدِكَ وَقُلْ بِاسْمِ اللَّهِ ‏.‏ ثَلاَثًا ‏.‏ وَقُلْ سَبْعَ مَرَّاتٍ أَعُوذُ بِاللَّهِ وَقُدْرَتِهِ مِنْ شَرِّ مَا أَجِدُ وَأُحَاذِرُ ‏"‏ ‏.‏ | F31: Sahih Muslim 2202 | G31: Book 39, Hadith 91 | H31: Sahih | I31: https://sunnah.com/muslim:2202
A32: 31 | B32: Illness & pain | C32: I visited Allah's Messenger (ﷺ) as he was running a high temperature. I touched his body with my hand and said to him: Allah's Messenger, you are running a high temperature, whereupon Allah's Messenger (ﷺ) said: Yes, it is so. I comparatively have a more severe fever than any one of you. I said: Is it because there is a double reward in store for you? Thereupon Allah's Messenger (ﷺ) said: Yes, it is so. And Allah's Messenger (ﷺ) again said: When a Muslim falls ill, his compensation is that his minor sins are obliterated just as leaves fall (in autumn). In the hadith transmitted on the authority of Zubair there is (no mention of these words):" I touched his body with my hands" | D32: Abdullah reported | E32: حَدَّثَنَا عُثْمَانُ بْنُ أَبِي شَيْبَةَ، وَزُهَيْرُ بْنُ حَرْبٍ، وَإِسْحَاقُ بْنُ إِبْرَاهِيمَ، قَالَ إِسْحَاقُ أَخْبَرَنَا وَقَالَ الآخَرَانِ، حَدَّثَنَا جَرِيرٌ، عَنِ الأَعْمَشِ، عَنْ إِبْرَاهِيمَ التَّيْمِيِّ، عَنِ الْحَارِثِ بْنِ سُوَيْدٍ، عَنْ عَبْدِ اللَّهِ، قَالَ دَخَلْتُ عَلَى رَسُولِ اللَّهِ صلى الله عليه وسلم وَهُوَ يُوعَكُ فَمَسِسْتُهُ بِيَدِي فَقُلْتُ يَا رَسُولَ اللَّهِ إِنَّكَ لَتُوعَكُ وَعْكًا شَدِيدًا ‏.‏ فَقَالَ رَسُولُ اللَّهِ صلى الله عليه وسلم ‏"‏ أَجَلْ إِنِّي أُوعَكُ كَمَا يُوعَكُ رَجُلاَنِ مِنْكُمْ ‏"‏ ‏.‏ قَالَ فَقُلْتُ ذَلِكَ أَنَّ لَكَ أَجْرَيْنِ فَقَالَ رَسُولُ اللَّهِ صلى الله عليه وسلم ‏"‏ أَجَلْ ‏"‏ ‏.‏ ثُمَّ قَالَ رَسُولُ اللَّهِ صلى الله عليه وسلم ‏"‏ مَا مِنْ مُسْلِمٍ يُصِيبُهُ أَذًى مِنْ مَرَضٍ فَمَا سِوَاهُ إِلاَّ حَطَّ اللَّهُ بِهِ سَيِّئَاتِهِ كَمَا تَحُطُّ الشَّجَرَةُ وَرَقَهَا ‏"‏ ‏.‏ وَلَيْسَ فِي حَدِيثِ زُهَيْرٍ فَمَسِسْتُهُ بِيَدِي ‏.‏ | F32: Sahih Muslim 2571a | G32: Book 45, Hadith 57 | H32: Sahih | I32: https://sunnah.com/muslim:2571a
A33: 32 | B33: Illness & pain | C33: Muhammad, have you fallen ill? Thereupon he said: Yes. He (Gabriel) said: "In the name of Allah I exorcise you from everything and safeguard you from every evil that may harm you and from the eye of a jealous one. Allah would cure you and I invoke the name of Allah for you" | D33: Abu Sa'id reported that Gabriel came to Allah's Messenger (ﷺ) and said | E33: حَدَّثَنَا بِشْرُ بْنُ هِلاَلٍ الصَّوَّافُ، حَدَّثَنَا عَبْدُ الْوَارِثِ، حَدَّثَنَا عَبْدُ الْعَزِيزِ بْنُ صُهَيْبٍ، عَنْ أَبِي نَضْرَةَ، عَنْ أَبِي سَعِيدٍ، أَنَّ جِبْرِيلَ، أَتَى النَّبِيَّ صلى الله عليه وسلم فَقَالَ يَا مُحَمَّدُ اشْتَكَيْتَ فَقَالَ ‏ "‏ نَعَمْ ‏"‏ ‏.‏ قَالَ بِاسْمِ اللَّهِ أَرْقِيكَ مِنْ كُلِّ شَىْءٍ يُؤْذِيكَ مِنْ شَرِّ كُلِّ نَفْسٍ أَوْ عَيْنِ حَاسِدٍ اللَّهُ يَشْفِيكَ بِاسْمِ اللَّهِ أَرْقِيكَ ‏.‏ | F33: Sahih Muslim 2186 | G33: Book 39, Hadith 54 | H33: Sahih | I33: https://sunnah.com/muslim:2186
A34: 33 | B34: Illness & pain | C34: Nigella seed is a remedy for every disease except death. | D34: Abu Huraira reported that he heard Allah's Messenger (ﷺ) as saying | E34: حَدَّثَنَا مُحَمَّدُ بْنُ رُمْحِ بْنِ الْمُهَاجِرِ، أَخْبَرَنَا اللَّيْثُ، عَنْ عُقَيْلٍ، عَنِ ابْنِ شِهَابٍ، أَخْبَرَنِي أَبُو سَلَمَةَ بْنُ عَبْدِ الرَّحْمَنِ، وَسَعِيدُ بْنُ الْمُسَيَّبِ، أَنَّ أَبَا هُرَيْرَةَ، أَخْبَرَهُمَا أَنَّهُ، سَمِعَ رَسُولَ اللَّهِ صلى الله عليه وسلم يَقُولُ ‏ "‏ إِنَّ فِي الْحَبَّةِ السَّوْدَاءِ شِفَاءً مِنْ كُلِّ دَاءٍ إِلاَّ السَّامَ ‏"‏ ‏.‏ وَالسَّامُ الْمَوْتُ ‏.‏ وَالْحَبَّةُ السَّوْدَاءُ الشُّونِيزُ ‏.‏ | F34: Sahih Muslim 2215a | G34: Book 39, Hadith 118 | H34: Sahih | I34: https://sunnah.com/muslim:2215a
A35: 34 | B35: Grief, loss & death of loved ones | C35: A man said to the Prophet, "My mother died suddenly, and I think that if she could speak, she would have given in charity. May I give in charity on her behalf?" He said, "Yes! Give in charity on her behalf" | D35: Narrated `Aisha | E35: حَدَّثَنَا إِسْمَاعِيلُ، قَالَ حَدَّثَنِي مَالِكٌ، عَنْ هِشَامٍ، عَنْ أَبِيهِ، عَنْ عَائِشَةَ، رضى الله عنها أَنَّ رَجُلاً، قَالَ لِلنَّبِيِّ صلى الله عليه وسلم إِنَّ أُمِّي افْتُلِتَتْ نَفْسَهَا، وَأُرَاهَا لَوْ تَكَلَّمَتْ تَصَدَّقَتْ، أَفَأَتَصَدَّقُ عَنْهَا قَالَ ‏ "‏ نَعَمْ، تَصَدَّقْ عَنْهَا ‏"‏‏.‏ | F35: Sahih al-Bukhari 2760 | G35: Book 55, Hadith 23 | H35: Sahih | I35: https://sunnah.com/bukhari:2760
A36: 35 | B36: Grief, loss & death of loved ones | C36: Allah's Messenger (ﷺ) said, "Allah says, 'I have nothing to give but Paradise as a reward to my believer slave, who, if I cause his dear friend (or relative) to die, remains patient (and hopes for Allah's Reward)" | D36: Narrated Abu Huraira | E36: حَدَّثَنَا قُتَيْبَةُ، حَدَّثَنَا يَعْقُوبُ بْنُ عَبْدِ الرَّحْمَنِ، عَنْ عَمْرٍو، عَنْ سَعِيدٍ الْمَقْبُرِيِّ، عَنْ أَبِي هُرَيْرَةَ، أَنَّ رَسُولَ اللَّهِ صلى الله عليه وسلم قَالَ ‏ "‏ يَقُولُ اللَّهُ تَعَالَى مَا لِعَبْدِي الْمُؤْمِنِ عِنْدِي جَزَاءٌ، إِذَا قَبَضْتُ صَفِيَّهُ مِنْ أَهْلِ الدُّنْيَا، ثُمَّ احْتَسَبَهُ إِلاَّ الْجَنَّةُ ‏"‏‏.‏ | F36: Sahih al-Bukhari 6424 | G36: Book 81, Hadith 13 | H36: Sahih | I36: https://sunnah.com/bukhari:6424
A37: 36 | B37: Grief, loss & death of loved ones | C37: The Prophet (ﷺ) said, "He who slaps the cheeks, tears the clothes and follows the traditions of the Days of Ignorance is not from us" | D37: Narrated `Abdullah | E37: حَدَّثَنَا عُمَرُ بْنُ حَفْصٍ، حَدَّثَنَا أَبِي، حَدَّثَنَا الأَعْمَشُ، عَنْ عَبْدِ اللَّهِ بْنِ مُرَّةَ، عَنْ مَسْرُوقٍ، عَنْ عَبْدِ اللَّهِ ـ رضى الله عنه ـ قَالَ قَالَ النَّبِيُّ صلى الله عليه وسلم ‏ "‏ لَيْسَ مِنَّا مَنْ ضَرَبَ الْخُدُودَ، وَشَقَّ الْجُيُوبَ، وَدَعَا بِدَعْوَى الْجَاهِلِيَّةِ ‏"‏‏.‏ | F37: Sahih al-Bukhari 1298 | G37: Book 23, Hadith 56 | H37: Sahih | I37: https://sunnah.com/bukhari:1298
A38: 37 | B38: Grief, loss & death of loved ones | C38: The Prophet (ﷺ) said, "A Muslim whose three children die before the age of puberty will be granted Paradise by Allah due to his mercy for them" | D38: Narrated Anas | E38: حَدَّثَنَا أَبُو مَعْمَرٍ، حَدَّثَنَا عَبْدُ الْوَارِثِ، حَدَّثَنَا عَبْدُ الْعَزِيزِ، عَنْ أَنَسٍ ـ رضى الله عنه ـ قَالَ قَالَ النَّبِيُّ صلى الله عليه وسلم ‏ "‏ مَا مِنَ النَّاسِ مِنْ مُسْلِمٍ يُتَوَفَّى لَهُ ثَلاَثٌ لَمْ يَبْلُغُوا الْحِنْثَ، إِلاَّ أَدْخَلَهُ اللَّهُ الْجَنَّةَ بِفَضْلِ رَحْمَتِهِ إِيَّاهُمْ ‏"‏‏.‏ | F38: Sahih al-Bukhari 1248 | G38: Book 23, Hadith 11 | H38: Sahih | I38: https://sunnah.com/bukhari:1248
A39: 38 | B39: Grief, loss & death of loved ones | C39: We went with Allah's Messenger (ﷺ) to the blacksmith Abu Saif, and he was the husband of the wet-nurse of Ibrahim (the son of the Prophet). Allah's Messenger (ﷺ) took Ibrahim and kissed him and smelled him and later we entered Abu Saif's house and at that time Ibrahim was in his last breaths, and the eyes of Allah's Messenger (ﷺ) started shedding tears. `Abdur Rahman bin `Auf said, "O Allah's Apostle, even you are weeping!" He said, "O Ibn `Auf, this is mercy." Then he wept more and said, "The eyes are shedding tears and the heart is grieved, and we will not say except what pleases our Lord, O Ibrahim ! Indeed we are grieved by your separation" | D39: Narrated Anas bin Malik | E39: حَدَّثَنَا الْحَسَنُ بْنُ عَبْدِ الْعَزِيزِ، حَدَّثَنَا يَحْيَى بْنُ حَسَّانَ، حَدَّثَنَا قُرَيْشٌ ـ هُوَ ابْنُ حَيَّانَ ـ عَنْ ثَابِتٍ، عَنْ أَنَسِ بْنِ مَالِكٍ ـ رضى الله عنه ـ قَالَ دَخَلْنَا مَعَ رَسُولِ اللَّهِ صلى الله عليه وسلم عَلَى أَبِي سَيْفٍ الْقَيْنِ ـ وَكَانَ ظِئْرًا لإِبْرَاهِيمَ ـ عَلَيْهِ السَّلاَمُ ـ فَأَخَذَ رَسُولُ اللَّهِ صلى الله عليه وسلم إِبْرَاهِيمَ فَقَبَّلَهُ وَشَمَّهُ، ثُمَّ دَخَلْنَا عَلَيْهِ بَعْدَ ذَلِكَ، وَإِبْرَاهِيمُ يَجُودُ بِنَفْسِهِ، فَجَعَلَتْ عَيْنَا رَسُولِ اللَّهِ صلى الله عليه وسلم تَذْرِفَانِ‏.‏ فَقَالَ لَهُ عَبْدُ الرَّحْمَنِ بْنُ عَوْفٍ ـ رضى الله عنه ـ وَأَنْتَ يَا رَسُولَ اللَّهِ فَقَالَ ‏"‏ يَا ابْنَ عَوْفٍ إِنَّهَا رَحْمَةٌ ‏"‏‏.‏ ثُمَّ أَتْبَعَهَا بِأُخْرَى فَقَالَ صلى الله عليه وسلم ‏"‏ إِنَّ الْعَيْنَ تَدْمَعُ، وَالْقَلْبَ يَحْزَنُ، وَلاَ نَقُولُ إِلاَّ مَا يَرْضَى رَبُّنَا، وَإِنَّا بِفِرَاقِكَ يَا إِبْرَاهِيمُ لَمَحْزُونُونَ ‏"‏‏.‏ رَوَاهُ مُوسَى عَنْ سُلَيْمَانَ بْنِ الْمُغِيرَةِ عَنْ ثَابِتٍ عَنْ أَنَسٍ ـ رضى الله عنه ـ عَنِ النَّبِيِّ صلى الله عليه وسلم‏.‏ | F39: Sahih al-Bukhari 1303 | G39: Book 23, Hadith 61 | H39: Sahih | I39: https://sunnah.com/bukhari:1303
A40: 39 | B40: Grief, loss & death of loved ones | C40: When the ailment of the Prophet (ﷺ) got aggravated, he became unconscious whereupon Fatima said, "Oh, how distressed my father is!" He said, "Your father will have no more distress after today." When he expired, she said, "O Father! Who has responded to the call of the Lord Who has invited him! O Father, whose dwelling place is the Garden of Paradise (i.e. Al-Firdaus)! O Father! We convey this news (of your death) to Gabriel." When he was buried, Fatima said, "O Anas! Do you feel pleased to throw earth over Allah's Messenger (ﷺ)?" | D40: Narrated Anas | E40: حَدَّثَنَا سُلَيْمَانُ بْنُ حَرْبٍ، حَدَّثَنَا حَمَّادٌ، عَنْ ثَابِتٍ، عَنْ أَنَسٍ، قَالَ لَمَّا ثَقُلَ النَّبِيُّ صلى الله عليه وسلم جَعَلَ يَتَغَشَّاهُ، فَقَالَتْ فَاطِمَةُ ـ عَلَيْهَا السَّلاَمُ ـ وَاكَرْبَ أَبَاهُ‏.‏ فَقَالَ لَهَا ‏ "‏ لَيْسَ عَلَى أَبِيكِ كَرْبٌ بَعْدَ الْيَوْمِ ‏"‏‏.‏ فَلَمَّا مَاتَ قَالَتْ يَا أَبَتَاهْ، أَجَابَ رَبًّا دَعَاهُ، يَا أَبَتَاهْ مَنْ جَنَّةُ الْفِرْدَوْسِ مَأْوَاهُ، يَا أَبَتَاهْ إِلَى جِبْرِيلَ نَنْعَاهْ‏.‏ فَلَمَّا دُفِنَ قَالَتْ فَاطِمَةُ ـ عَلَيْهَا السَّلاَمُ ـ يَا أَنَسُ، أَطَابَتْ أَنْفُسُكُمْ أَنْ تَحْثُوا عَلَى رَسُولِ اللَّهِ صلى الله عليه وسلم التُّرَابَ | F40: Sahih al-Bukhari 4462 | G40: Book 64, Hadith 478 | H40: Sahih | I40: https://sunnah.com/bukhari:4462
A41: 40 | B41: Grief, loss & death of loved ones | C41: The daughter of the Prophet (ﷺ) sent (a messenger) to the Prophet (ﷺ) requesting him to come as her child was dying (or was gasping), but the Prophet (ﷺ) returned the messenger and told him to convey his greeting to her and say: "Whatever Allah takes is for Him and whatever He gives, is for Him, and everything with Him has a limited fixed term (in this world) and so she should be patient and hope for Allah's reward." She again sent for him, swearing that he should come. The Prophet (ﷺ) got up, and so did Sa`d bin 'Ubada, Mu`adh bin Jabal, Ubai bin Ka`b, Zaid bin Thabit and some other men. The child was brought to Allah's Messenger (ﷺ) while his breath was disturbed in his chest (the sub-narrator thinks that Usama added: ) as if it was a leather water-skin. On that the eyes of the Prophet (ﷺ) started shedding tears. Sa`d said, "O Allah's Messenger (ﷺ)! What is this?" He replied, "It is mercy which Allah has lodged in the hearts of His slaves, and Allah is merciful only to those of His slaves who are merciful (to others)" | D41: Narrated Usama bin Zaid | E41: حَدَّثَنَا عَبْدَانُ، وَمُحَمَّدٌ، قَالاَ أَخْبَرَنَا عَبْدُ اللَّهِ، أَخْبَرَنَا عَاصِمُ بْنُ سُلَيْمَانَ، عَنْ أَبِي عُثْمَانَ، قَالَ حَدَّثَنِي أُسَامَةُ بْنُ زَيْدٍ ـ رضى الله عنهما ـ قَالَ أَرْسَلَتِ ابْنَةُ النَّبِيِّ صلى الله عليه وسلم إِلَيْهِ إِنَّ ابْنًا لِي قُبِضَ فَائْتِنَا‏.‏ فَأَرْسَلَ يُقْرِئُ السَّلاَمَ وَيَقُولُ ‏"‏ إِنَّ لِلَّهِ مَا أَخَذَ وَلَهُ مَا أَعْطَى وَكُلٌّ عِنْدَهُ بِأَجَلٍ مُسَمًّى، فَلْتَصْبِرْ وَلْتَحْتَسِبْ ‏"‏‏.‏ فَأَرْسَلَتْ إِلَيْهِ تُقْسِمُ عَلَيْهِ لَيَأْتِيَنَّهَا، فَقَامَ وَمَعَهُ سَعْدُ بْنُ عُبَادَةَ وَمُعَاذُ بْنُ جَبَلٍ وَأُبَىُّ بْنُ كَعْبٍ وَزَيْدُ بْنُ ثَابِتٍ وَرِجَالٌ، فَرُفِعَ إِلَى رَسُولِ اللَّهِ صلى الله عليه وسلم الصَّبِيُّ وَنَفْسُهُ تَتَقَعْقَعُ ـ قَالَ حَسِبْتُهُ أَنَّهُ قَالَ ـ كَأَنَّهَا شَنٌّ‏.‏ فَفَاضَتْ عَيْنَاهُ‏.‏ فَقَالَ سَعْدٌ يَا رَسُولَ اللَّهِ مَا هَذَا فَقَالَ ‏"‏ هَذِهِ رَحْمَةٌ جَعَلَهَا اللَّهُ فِي قُلُوبِ عِبَادِهِ، وَإِنَّمَا يَرْحَمُ اللَّهُ مِنْ عِبَادِهِ الرُّحَمَاءَ ‏"‏‏.‏ | F41: Sahih al-Bukhari 1284 | G41: Book 23, Hadith 44 | H41: Sahih | I41: https://sunnah.com/bukhari:1284
A42: 41 | B42: Grief, loss & death of loved ones | C42: Aisha used to recommend at-Talbina for the sick and for such a person as grieved over a dead person. She used to say, "I heard Allah's Messenger (ﷺ) saying, 'at-Talbina gives rest to the heart of the patient and makes it active and relieves some of his sorrow and grief" | D42: Narrated 'Urwa | E42: حَدَّثَنَا حِبَّانُ بْنُ مُوسَى، أَخْبَرَنَا عَبْدُ اللَّهِ، أَخْبَرَنَا يُونُسُ بْنُ يَزِيدَ، عَنْ عُقَيْلٍ، عَنِ ابْنِ شِهَابٍ، عَنْ عُرْوَةَ، عَنْ عَائِشَةَ ـ رضى الله عنها ـ أَنَّهَا كَانَتْ تَأْمُرُ بِالتَّلْبِينِ لِلْمَرِيضِ وَلِلْمَحْزُونِ عَلَى الْهَالِكِ، وَكَانَتْ تَقُولُ إِنِّي سَمِعْتُ رَسُولَ اللَّهِ صلى الله عليه وسلم يَقُولُ ‏ "‏ إِنَّ التَّلْبِينَةَ تُجِمُّ فُؤَادَ الْمَرِيضِ، وَتَذْهَبُ بِبَعْضِ الْحُزْنِ ‏"‏‏.‏ | F42: Sahih al-Bukhari 5689 | G42: Book 76, Hadith 12 | H42: Sahih | I42: https://sunnah.com/bukhari:5689
A43: 42 | B43: Grief, loss & death of loved ones | C43: The Prophet (ﷺ) said, "Relieved or relieving. And a believer is relieved (by death)" | D43: Narrated Abu Qatada | E43: حَدَّثَنَا مُسَدَّدٌ، حَدَّثَنَا يَحْيَى، عَنْ عَبْدِ رَبِّهِ بْنِ سَعِيدٍ، عَنْ مُحَمَّدِ بْنِ عَمْرِو بْنِ حَلْحَلَةَ، حَدَّثَنِي ابْنُ كَعْبٍ، عَنْ أَبِي قَتَادَةَ، عَنِ النَّبِيِّ صلى الله عليه وسلم قَالَ ‏ "‏ مُسْتَرِيحٌ، وَمُسْتَرَاحٌ مِنْهُ، الْمُؤْمِنُ يَسْتَرِيحُ ‏"‏‏.‏ | F43: Sahih al-Bukhari 6513 | G43: Book 81, Hadith 102 | H43: Sahih | I43: https://sunnah.com/bukhari:6513
... A45: 44 | B45: Grief, loss & death of loved ones | C45: Whenever you visit the sick or the dead, supplicate for good because angels say" Amen" to whatever you say. She added: When Abu Salama died, I went to the Messenger of Allah (ﷺ) and said: Messenger of Allah, Abu Salama has died. He told me to recite:" O Allah! forgive me and him (Abu Salama) and give me a better substitute than he." So I said (this), and Allah gave me in exchange Muhammad, who is better for me than him (Abu Salama) | D45: Umm Salama reported Allah's Messenger (ﷺ) as saying | E45: حَدَّثَنَا أَبُو بَكْرِ بْنُ أَبِي شَيْبَةَ، وَأَبُو كُرَيْبٍ قَالاَ حَدَّثَنَا أَبُو مُعَاوِيَةَ، عَنِ الأَعْمَشِ، عَنْ شَقِيقٍ، عَنْ أُمِّ سَلَمَةَ، قَالَتْ قَالَ رَسُولُ اللَّهِ صلى الله عليه وسلم ‏"‏ إِذَا حَضَرْتُمُ الْمَرِيضَ أَوِ الْمَيِّتَ فَقُولُوا خَيْرًا فَإِنَّ الْمَلاَئِكَةَ يُؤَمِّنُونَ عَلَى مَا تَقُولُونَ ‏"‏ ‏.‏ قَالَتْ فَلَمَّا مَاتَ أَبُو سَلَمَةَ أَتَيْتُ النَّبِيَّ صلى الله عليه وسلم فَقُلْتُ يَا رَسُولَ اللَّهِ إِنَّ أَبَا سَلَمَةَ قَدْ مَاتَ قَالَ ‏"‏ قُولِي اللَّهُمَّ اغْفِرْ لِي وَلَهُ وَأَعْقِبْنِي مِنْهُ عُقْبَى حَسَنَةً ‏"‏ ‏.‏ قَالَتْ فَقُلْتُ فَأَعْقَبَنِي اللَّهُ مَنْ هُوَ خَيْرٌ لِي مِنْهُ مُحَمَّدًا صلى الله عليه وسلم ‏.‏ | F45: Sahih Muslim 919 | G45: Book 11, Hadith 7 | H45: Sahih | I45: https://sunnah.com/muslim:919
A46: 45 | B46: Grief, loss & death of loved ones | C46: Abdullah b. 'Umar said that Sa'd b. Ubada complained of illness. The Messenger of Allah (ﷺ) came to visit him accompanied by 'Abd al-Rahman b. 'Auf, Sa'd b. Abi Waqqas and 'Abdullah b. Mas'ud. As he entered (his room) he found him in a swoon. Upon this he said:Has he died? They said: Messenger of Allah, it is not so. The Messenger of Allah (ﷺ) wept. When the people saw Allah's Messenger (ﷺ) weeping, they also began to weep. He said. Listen, Allah does not punish for the tears that the eye sheds or the grief the heart feels, but He punishes for this (pointing to his tongue), or He may show mercy. | E46: حَدَّثَنَا يُونُسُ بْنُ عَبْدِ الأَعْلَى الصَّدَفِيُّ، وَعَمْرُو بْنُ سَوَّادٍ الْعَامِرِيُّ، قَالاَ أَخْبَرَنَا عَبْدُ اللَّهِ بْنُ وَهْبٍ، أَخْبَرَنِي عَمْرُو بْنُ الْحَارِثِ، عَنْ سَعِيدِ بْنِ الْحَارِثِ الأَنْصَارِيِّ، عَنْ عَبْدِ، اللَّهِ بْنِ عُمَرَ قَالَ اشْتَكَى سَعْدُ بْنُ عُبَادَةَ شَكْوَى لَهُ فَأَتَى رَسُولُ اللَّهِ صلى الله عليه وسلم يَعُودُهُ مَعَ عَبْدِ الرَّحْمَنِ بْنِ عَوْفٍ وَسَعْدِ بْنِ أَبِي وَقَّاصٍ وَعَبْدِ اللَّهِ بْنِ مَسْعُودٍ فَلَمَّا دَخَلَ عَلَيْهِ وَجَدَهُ فِي غَشِيَّةٍ فَقَالَ ‏"‏ أَقَدْ قَضَى ‏"‏ ‏.‏ قَالُوا لاَ يَا رَسُولَ اللَّهِ ‏.‏ فَبَكَى رَسُولُ اللَّهِ صلى الله عليه وسلم فَلَمَّا رَأَى الْقَوْمُ بُكَاءَ رَسُولِ اللَّهِ صلى الله عليه وسلم بَكَوْا فَقَالَ ‏"‏ أَلاَ تَسْمَعُونَ إِنَّ اللَّهَ لاَ يُعَذِّبُ بِدَمْعِ الْعَيْنِ وَلاَ بِحُزْنِ الْقَلْبِ وَلَكِنْ يُعَذِّبُ بِهَذَا - وَأَشَارَ إِلَى لِسَانِهِ - أَوْ يَرْحَمُ ‏"‏ ‏.‏ | F46: Sahih Muslim 924 | G46: Book 11, Hadith 15 | H46: Sahih | I46: https://sunnah.com/muslim:924
A47: 46 | B47: Grief, loss & death of loved ones | C47: Let us visit Umm Aiman as Allah's Messenger (ﷺ) used to visit her. As we came to her, she wept. They (Abu Bakr and Umar) said to her: What makes you weep? What is in store (in the next world) for Allah's-Messenger (ﷺ) is better than (this worldly life). She said: I weep not because I am ignorant of the fact that what is in store for Allah's Messenger (ﷺ) (in the next world) is better than (this world), but I weep because the revelation which came from the Heaven has ceased to come. This moved both of them to tears and they began to weep along with her. | D47: Anas reported that after the death of Allah's Messenger (ﷺ) Abu Bakr said to 'Umar | E47: حَدَّثَنَا زُهَيْرُ بْنُ حَرْبٍ، أَخْبَرَنِي عَمْرُو بْنُ عَاصِمٍ الْكِلاَبِيُّ، حَدَّثَنَا سُلَيْمَانُ بْنُ الْمُغِيرَةِ، عَنْ ثَابِتٍ، عَنْ أَنَسٍ، قَالَ قَالَ أَبُو بَكْرٍ رضى الله عنه بَعْدَ وَفَاةِ رَسُولِ اللَّهِ صلى الله عليه وسلم لِعُمَرَ انْطَلِقْ بِنَا إِلَى أُمِّ أَيْمَنَ نَزُورُهَا كَمَا كَانَ رَسُولُ اللَّهِ صلى الله عليه وسلم يَزُورُهَا ‏.‏ فَلَمَّا انْتَهَيْنَا إِلَيْهَا بَكَتْ فَقَالاَ لَهَا مَا يُبْكِيكِ مَا عِنْدَ اللَّهِ خَيْرٌ لِرَسُولِهِ صلى الله عليه وسلم ‏.‏ فَقَالَتْ مَا أَبْكِي أَنْ لاَ أَكُونَ أَعْلَمُ أَنَّ مَا عِنْدَ اللَّهِ خَيْرٌ لِرَسُولِهِ صلى الله عليه وسلم وَلَكِنْ أَبْكِي أَنَّ الْوَحْىَ قَدِ انْقَطَعَ مِنَ السَّمَاءِ ‏.‏ فَهَيَّجَتْهُمَا عَلَى الْبُكَاءِ فَجَعَلاَ يَبْكِيَانِ مَعَهَا ‏.‏ | F47: Sahih Muslim 2454 | G47: Book 44, Hadith 148 | H47: Sahih | I47: https://sunnah.com/muslim:2454
A48: 47 | B48: Grief, loss & death of loved ones | C48: Allah's Messenger, men receive your instructions; kindly allocate at your convenience a day for us also, on which we would come to you and you would teach us what Allah has taught you. He said: You assemble on such and such a day. They assembled and Allah's Messenger (ﷺ) came to them and taught them what Allah had taught him and he then said: No woman amongst you who sends her three children as her forerunners (in the Hereafter) but they would serve him as a protection against Hell-Fire. A woman said: What about two and two and two? Thereupon Allah's Messenger (ﷺ) said: Even if they are two and two and two. | D48: Abu Sa'id Khudri reported that a woman came to Allah's Messenger (ﷺ) and said | E48: حَدَّثَنَا أَبُو كَامِلٍ الْجَحْدَرِيُّ، فُضَيْلُ بْنُ حُسَيْنٍ حَدَّثَنَا أَبُو عَوَانَةَ، عَنْ عَبْدِ الرَّحْمَنِ، بْنِ الأَصْبَهَانِيِّ عَنْ أَبِي صَالِحٍ، ذَكْوَانَ عَنْ أَبِي سَعِيدٍ الْخُدْرِيِّ، قَالَ جَاءَتِ امْرَأَةٌ إِلَى رَسُولِ اللَّهِ صلى الله عليه وسلم فَقَالَتْ يَا رَسُولَ اللَّهِ ذَهَبَ الرِّجَالُ بِحَدِيثِكَ فَاجْعَلْ لَنَا مِنْ نَفْسِكَ يَوْمًا نَأْتِيكَ فِيهِ تُعَلِّمُنَا مِمَّا عَلَّمَكَ اللَّهُ ‏.‏ قَالَ ‏"‏ اجْتَمِعْنَ يَوْمَ كَذَا وَكَذَا ‏"‏ ‏.‏ فَاجْتَمَعْنَ فَأَتَاهُنَّ رَسُولُ اللَّهِ صلى الله عليه وسلم فَعَلَّمَهُنَّ مِمَّا عَلَّمَهُ اللَّهُ ثُمَّ قَالَ ‏"‏ مَا مِنْكُنَّ مِنِ امْرَأَةٍ تُقَدِّمُ بَيْنَ يَدَيْهَا مِنْ وَلَدِهَا ثَلاَثَةً إِلاَّ كَانُوا لَهَا حِجَابًا مِنَ النَّارِ ‏"‏ ‏.‏ فَقَالَتِ امْرَأَةٌ وَاثْنَيْنِ وَاثْنَيْنِ وَاثْنَيْنِ فَقَالَ رَسُولُ اللَّهِ صلى الله عليه وسلم ‏"‏ وَاثْنَيْنِ وَاثْنَيْنِ وَاثْنَيْنِ ‏"‏ ‏.‏ | F48: Sahih Muslim 2633 | G48: Book 45, Hadith 196 | H48: Sahih | I48: https://sunnah.com/muslim:2633
A49: 48 | B49: Grief, loss & death of loved ones | C49: Jubair b. Nufair says:I heard it from 'Auf b. Malik that the Prophet (ﷺ) said prayer on the dead body, and I remembered his prayer:" O Allah! forgive him, have mercy upon him, give him peace and absolve him. Receive him with honour and make his grave spacious; wash him with water, snow and hail. Cleanse him from faults as Thou wouldst cleanse a white garment from impurity. Requite him with an abode more excellent than his abode, with a family better than his family, and with a mate better than his mate. Admit him to the Garden, and protect him from the torment of the grave and the torment of the Fire." ('Auf bin Malik) said: I earnestly desired that I were this dead body. | E49: وَحَدَّثَنِي هَارُونُ بْنُ سَعِيدٍ الأَيْلِيُّ، أَخْبَرَنَا ابْنُ وَهْبٍ، أَخْبَرَنِي مُعَاوِيَةُ بْنُ صَالِحٍ، عَنْ حَبِيبِ بْنِ عُبَيْدٍ، عَنْ جُبَيْرِ بْنِ نُفَيْرٍ، سَمِعَهُ يَقُولُ سَمِعْتُ عَوْفَ بْنَ مَالِكٍ، يَقُولُ صَلَّى رَسُولُ اللَّهِ صلى الله عليه وسلم عَلَى جَنَازَةٍ فَحَفِظْتُ مِنْ دُعَائِهِ وَهُوَ يَقُولُ ‏ "‏ اللَّهُمَّ اغْفِرْ لَهُ وَارْحَمْهُ وَعَافِهِ وَاعْفُ عَنْهُ وَأَكْرِمْ نُزُلَهُ وَوَسِّعْ مُدْخَلَهُ وَاغْسِلْهُ بِالْمَاءِ وَالثَّلْجِ وَالْبَرَدِ وَنَقِّهِ مِنَ الْخَطَايَا كَمَا نَقَّيْتَ الثَّوْبَ الأَبْيَضَ مِنَ الدَّنَسِ وَأَبْدِلْهُ دَارًا خَيْرًا مِنْ دَارِهِ وَأَهْلاً خَيْرًا مِنْ أَهْلِهِ وَزَوْجًا خَيْرًا مِنْ زَوْجِهِ وَأَدْخِلْهُ الْجَنَّةَ وَأَعِذْهُ مِنْ عَذَابِ الْقَبْرِ أَوْ مِنْ عَذَابِ النَّارِ ‏"‏ ‏.‏ قَالَ حَتَّى تَمَنَّيْتُ أَنْ أَكُونَ أَنَا ذَلِكَ الْمَيِّتَ ‏.‏ قَالَ وَحَدَّثَنِي عَبْدُ الرَّحْمَنِ بْنُ جُبَيْرٍ حَدَّثَهُ عَنْ أَبِيهِ عَنْ عَوْفِ بْنِ مَالِكٍ عَنِ النَّبِيِّ صلى الله عليه وسلم بِنَحْوِ هَذَا الْحَدِيثِ أَيْضًا ‏.‏ | F49: Sahih Muslim 963b | G49: Book 11, Hadith 109 | H49: Sahih | I49: https://sunnah.com/muslim:963b
A50: 49 | B50: Grief, loss & death of loved ones | C50: “Allah says: ‘O son of Adam! If you are patient and seek reward at the moment of first shock, I will not approve of any reward for you less than Paradise.’” | D50: It was narrated from Abu Umamah that the Prophet (ﷺ) said | E50: حَدَّثَنَا هِشَامُ بْنُ عَمَّارٍ، حَدَّثَنَا إِسْمَاعِيلُ بْنُ عَيَّاشٍ، حَدَّثَنَا ثَابِتُ بْنُ عَجْلاَنَ، عَنِ الْقَاسِمِ، عَنْ أَبِي أُمَامَةَ، عَنِ النَّبِيِّ ـ صلى الله عليه وسلم ـ قَالَ: ‏ "‏ يَقُولُ اللَّهُ سُبْحَانَهُ: ابْنَ آدَمَ إِنْ صَبَرْتَ وَاحْتَسَبْتَ عِنْدَ الصَّدْمَةِ الأُولَى لَمْ أَرْضَ لَكَ ثَوَابًا دُونَ الْجَنَّةِ ‏"‏ ‏.‏ | F50: Sunan Ibn Majah 1597 | G50: Book 6, Hadith 165 | H50: Hasan (Al-Albani) | I50: https://sunnah.com/ibnmajah:1597
A51: 50 | B51: Worry, anxiety & distress | C51: Allah's Messenger (ﷺ) used to say at a time of distress, "La ilaha illal-lahu Rabbul-l-'arsh il-'azim, La ilaha illallahu Rabbu-s-samawati wa Rabbu-l-ard, Rabbu-l-'arsh-il-Karim" | D51: Narrated Ibn `Abbas | E51: حَدَّثَنَا مُسَدَّدٌ، حَدَّثَنَا يَحْيَى، عَنْ هِشَامِ بْنِ أَبِي عَبْدِ اللَّهِ، عَنْ قَتَادَةَ، عَنْ أَبِي الْعَالِيَةِ، عَنِ ابْنِ عَبَّاسٍ، أَنَّ رَسُولَ اللَّهِ صلى الله عليه وسلم كَانَ يَقُولُ عِنْدَ الْكَرْبِ ‏ "‏ لاَ إِلَهَ إِلاَّ اللَّهُ الْعَظِيمُ الْحَلِيمُ، لاَ إِلَهَ إِلاَّ اللَّهُ رَبُّ الْعَرْشِ الْعَظِيمِ، لاَ إِلَهَ إِلاَّ اللَّهُ رَبُّ السَّمَوَاتِ، وَرَبُّ الأَرْضِ، وَرَبُّ الْعَرْشِ الْكَرِيمِ ‏"‏‏.‏ وَقَالَ وَهْبٌ حَدَّثَنَا شُعْبَةُ عَنْ قَتَادَةَ مِثْلَهُ‏.‏ | F51: Sahih al-Bukhari 6346 | G51: Book 80, Hadith 43 | H51: Sahih | I51: https://sunnah.com/bukhari:6346
A52: 51 | B52: Worry, anxiety & distress | C52: The Prophet (ﷺ) used to say, "O Allah! I seek refuge with You from worry and grief, from incapacity and laziness, from cowardice and miserliness, from being heavily in debt and from being overpowered by (other) men." (See Hadith No) | D52: Narrated Anas bin Malik | E52: حَدَّثَنَا خَالِدُ بْنُ مَخْلَدٍ، حَدَّثَنَا سُلَيْمَانُ، قَالَ حَدَّثَنِي عَمْرُو بْنُ أَبِي عَمْرٍو، قَالَ سَمِعْتُ أَنَسًا، قَالَ كَانَ النَّبِيُّ صلى الله عليه وسلم يَقُولُ ‏ "‏ اللَّهُمَّ إِنِّي أَعُوذُ بِكَ مِنَ الْهَمِّ وَالْحَزَنِ، وَالْعَجْزِ وَالْكَسَلِ، وَالْجُبْنِ وَالْبُخْلِ، وَضَلَعِ الدَّيْنِ، وَغَلَبَةِ الرِّجَالِ ‏"‏‏.‏ | F52: Sahih al-Bukhari 6369 | G52: Book 80, Hadith 66 | H52: Sahih | I52: https://sunnah.com/bukhari:6369
A53: 52 | B53: Worry, anxiety & distress | C53: The Prophet (ﷺ) used to invoke Allah at the time of distress, saying, "La ilaha illal-lahu Al-`Azim, al- Halim, La ilaha illal-lahu Rabbu-s-samawati wal-ard wa Rabbu-l-arsh il-azim" | D53: Narrated Ibn `Abbas | E53: حَدَّثَنَا مُسْلِمُ بْنُ إِبْرَاهِيمَ، حَدَّثَنَا هِشَامٌ، حَدَّثَنَا قَتَادَةُ، عَنْ أَبِي الْعَالِيَةِ، عَنِ ابْنِ عَبَّاسٍ ـ رضى الله عنهما ـ قَالَ كَانَ النَّبِيُّ صلى الله عليه وسلم يَدْعُو عِنْدَ الْكَرْبِ ‏ "‏ لاَ إِلَهَ إِلاَّ اللَّهُ الْعَظِيمُ الْحَلِيمُ، لاَ إِلَهَ إِلاَّ اللَّهُ رَبُّ السَّمَوَاتِ وَالأَرْضِ، رَبُّ الْعَرْشِ الْعَظِيمِ ‏"‏‏.‏ | F53: Sahih al-Bukhari 6345 | G53: Book 80, Hadith 42 | H53: Sahih | I53: https://sunnah.com/bukhari:6345
A54: 53 | B54: Worry, anxiety & distress | C54: The Prophet (ﷺ) said, "Allah has accepted my invocation to forgive what whispers in the hearts of my followers, unless they put it to action or utter it." (See Hadith No. 657 Vol) | D54: Narrated Abu Huraira | E54: حَدَّثَنَا الْحُمَيْدِيُّ، حَدَّثَنَا سُفْيَانُ، حَدَّثَنَا مِسْعَرٌ، عَنْ قَتَادَةَ، عَنْ زُرَارَةَ بْنِ أَوْفَى، عَنْ أَبِي هُرَيْرَةَ ـ رضى الله عنه ـ قَالَ قَالَ النَّبِيُّ صلى الله عليه وسلم ‏ "‏ إِنَّ اللَّهَ تَجَاوَزَ لِي عَنْ أُمَّتِي مَا وَسْوَسَتْ بِهِ صُدُورُهَا، مَا لَمْ تَعْمَلْ أَوْ تَكَلَّمْ ‏"‏‏.‏ | F54: Sahih al-Bukhari 2528 | G54: Book 49, Hadith 12 | H54: Sahih | I54: https://sunnah.com/bukhari:2528
A55: 54 | B55: Worry, anxiety & distress | C55: If anyone sees a dream which he does not like, he should spit on his left side three times, and seek refuge with Allah from the Satan three times, and let him turn over from the side on which he was sleeping. | D55: Jabir reported Allah's Messenger (ﷺ) as saying | E55: حَدَّثَنَا قُتَيْبَةُ بْنُ سَعِيدٍ، حَدَّثَنَا لَيْثٌ، ح وَحَدَّثَنَا ابْنُ رُمْحٍ، أَخْبَرَنَا اللَّيْثُ، عَنْ أَبِي، الزُّبَيْرِ عَنْ جَابِرٍ، عَنْ رَسُولِ اللَّهِ صلى الله عليه وسلم أَنَّهُ قَالَ ‏ "‏ إِذَا رَأَى أَحَدُكُمُ الرُّؤْيَا يَكْرَهُهَا فَلْيَبْصُقْ عَنْ يَسَارِهِ ثَلاَثًا وَلْيَسْتَعِذْ بِاللَّهِ مِنَ الشَّيْطَانِ ثَلاَثًا وَلْيَتَحَوَّلْ عَنْ جَنْبِهِ الَّذِي كَانَ عَلَيْهِ ‏"‏ ‏.‏ | F55: Sahih Muslim 2262 | G55: Book 42, Hadith 8 | H55: Sahih | I55: https://sunnah.com/muslim:2262
A56: 55 | B56: Worry, anxiety & distress | C56: We were in the company of Allah's Messenger (ﷺ) and he delivered to us a sermon and made a mention of Hell-Fire. Then I came to my house and began to laugh with my children and sport with my wife. (Hanzala) further reported: I went out and met Abu Bakr and made a mention of that to him. Thereupon he said: I have done the same as you have mentioned. So we went to see Allah's Messenger (ﷺ) and said to him: Allah's Messenger, Hanzala has turned to he a hypocrite. And he (the Holy Prophet) said Show respite. And then I narrated to him the story, and Abu Bakr said: I have done the same as he has done. Thereupon he (the Holy Prophet) said: Hanzala, there is a time for worldly affairs and a time for (worship and devotion), and if your state of mind is always the same as it is at the time of remembrance of Allah, the Angels would shake hands with you and would greet you on the path by saying: As-Salamu-Alaikum. | D56: Hanzala reported | E56: حَدَّثَنِي إِسْحَاقُ بْنُ مَنْصُورٍ، أَخْبَرَنَا عَبْدُ الصَّمَدِ، سَمِعْتُ أَبِي يُحَدِّثُ، حَدَّثَنَا سَعِيدٌ، الْجُرَيْرِيُّ عَنْ أَبِي عُثْمَانَ النَّهْدِيِّ، عَنْ حَنْظَلَةَ، قَالَ كُنَّا عِنْدَ رَسُولِ اللَّهِ صلى الله عليه وسلم فَوَعَظَنَا فَذَكَّرَ النَّارَ - قَالَ - ثُمَّ جِئْتُ إِلَى الْبَيْتِ فَضَاحَكْتُ الصِّبْيَانَ وَلاَعَبْتُ الْمَرْأَةَ - قَالَ - فَخَرَجْتُ فَلَقِيتُ أَبَا بَكْرٍ فَذَكَرْتُ ذَلِكَ لَهُ فَقَالَ وَأَنَا قَدْ فَعَلْتُ مِثْلَ مَا تَذْكُرُ ‏.‏ فَلَقِينَا رَسُولَ اللَّهِ صلى الله عليه وسلم فَقُلْتُ يَا رَسُولَ اللَّهِ نَافَقَ حَنْظَلَةُ فَقَالَ ‏"‏ مَهْ ‏"‏ ‏.‏ فَحَدَّثْتُهُ بِالْحَدِيثِ فَقَالَ أَبُو بَكْرٍ وَأَنَا قَدْ فَعَلْتُ مِثْلَ مَا فَعَلَ فَقَالَ ‏"‏ يَا حَنْظَلَةُ سَاعَةً وَسَاعَةً وَلَوْ كَانَتْ تَكُونُ قُلُوبُكُمْ كَمَا تَكُونُ عِنْدَ الذِّكْرِ لَصَافَحَتْكُمُ الْمَلاَئِكَةُ حَتَّى تُسَلِّمَ عَلَيْكُمْ فِي الطُّرُقِ ‏"‏ ‏.‏ | F56: Sahih Muslim 2750b | G56: Book 50, Hadith 15 | H56: Sahih | I56: https://sunnah.com/muslim:2750b
A57: 56 | B57: Worry, anxiety & distress | C57: Never a believer is stricken with discomfort, hardship or illness, grief or even with mental worry that his sins are not expiated for him. | D57: Abu Sa'id and abu Huraira reported that they heard Allah's Messenger (ﷺ) as saying | E57: حَدَّثَنَا أَبُو بَكْرِ بْنُ أَبِي شَيْبَةَ، وَأَبُو كُرَيْبٍ قَالاَ حَدَّثَنَا أَبُو أُسَامَةَ، عَنِ الْوَلِيدِ بْنِ، كَثِيرٍ عَنْ مُحَمَّدِ بْنِ عَمْرِو بْنِ عَطَاءٍ، عَنْ عَطَاءِ بْنِ يَسَارٍ، عَنْ أَبِي سَعِيدٍ، وَأَبِي، هُرَيْرَةَ أَنَّهُمَا سَمِعَا رَسُولَ اللَّهِ صلى الله عليه وسلم يَقُولُ ‏ "‏ مَا يُصِيبُ الْمُؤْمِنَ مِنْ وَصَبٍ وَلاَ نَصَبٍ وَلاَ سَقَمٍ وَلاَ حَزَنٍ حَتَّى الْهَمِّ يُهَمُّهُ إِلاَّ كُفِّرَ بِهِ مِنْ سَيِّئَاتِهِ ‏"‏ ‏.‏ | F57: Sahih Muslim 2573 | G57: Book 45, Hadith 66 | H57: Sahih | I57: https://sunnah.com/muslim:2573
A58: 57 | B58: Worry, anxiety & distress | C58: “Whenever a matter would distress him, the Prophet (ﷺ) would say: ‘O Living, O Self-Sustaining Sustainer! In Your Mercy do I seek relief (Yā Ḥayyu yā Qayyūm, bi-raḥmatika astaghīth).’” And with this chain, that he said: “The Messenger of Allah (ﷺ) said: ‘Be constant with: “O Possessor of Majesty and Honor (Yā Dhal-Jalāli wal-Ikrām).’”” | D58: Anas bin Malik said | E58: حَدَّثَنَا مُحَمَّدُ بْنُ حَاتِمٍ الْمُكْتِبُ، حَدَّثَنَا أَبُو بَدْرٍ، شُجَاعُ بْنُ الْوَلِيدِ عَنِ الرُّحَيْلِ بْنِ مُعَاوِيَةَ، أَخِي زُهَيْرِ بْنِ مُعَاوِيَةَ عَنِ الرَّقَاشِيِّ، عَنْ أَنَسِ بْنِ مَالِكٍ، قَالَ كَانَ النَّبِيُّ صلى الله عليه وسلم إِذَا كَرَبَهُ أَمْرٌ قَالَ ‏"‏ يَا حَىُّ يَا قَيُّومُ بِرَحْمَتِكَ أَسْتَغِيثُ ‏"‏ ‏.‏ وَبِإِسْنَادِهِ قَالَ قَالَ رَسُولُ اللَّهِ صلى الله عليه وسلم ‏"‏ أَلِظُّوا بِيَا ذَا الْجَلاَلِ وَالإِكْرَامِ ‏"‏ ‏.‏ قَالَ أَبُو عِيسَى هَذَا حَدِيثٌ غَرِيبٌ ‏.‏ وَقَدْ رُوِيَ هَذَا الْحَدِيثُ عَنْ أَنَسٍ مِنْ غَيْرِ هَذَا الْوَجْهِ ‏.‏ | F58: Jami' at-Tirmidhi 3524 | G58: Book 48, Hadith 155 | H58: Hasan (Al-Albani) | I58: https://sunnah.com/tirmidhi:3524
A59: 58 | B59: Worry, anxiety & distress | C59: Salim ibn AbulJa'dah said: A man said: (Mis'ar said: I think he was from the tribe of Khuza'ah): would that I had prayed, and got comfort. The people objected to him for it. Thereupon he said: I heard the Messenger of Allah (ﷺ) as saying: O Bilal, call iqamah for prayer: give us comfort by it. | D59: Narrated A man | E59: حَدَّثَنَا مُسَدَّدٌ، حَدَّثَنَا عِيسَى بْنُ يُونُسَ، حَدَّثَنَا مِسْعَرُ بْنُ كِدَامٍ، عَنْ عَمْرِو بْنِ مُرَّةَ، عَنْ سَالِمِ بْنِ أَبِي الْجَعْدِ، قَالَ قَالَ رَجُلٌ - قَالَ مِسْعَرٌ أُرَاهُ مِنْ خُزَاعَةَ - لَيْتَنِي صَلَّيْتُ فَاسْتَرَحْتُ فَكَأَنَّهُمْ عَابُوا عَلَيْهِ ذَلِكَ فَقَالَ سَمِعْتُ رَسُولَ اللَّهِ صلى الله عليه وسلم يَقُولُ ‏ "‏ يَا بِلاَلُ أَقِمِ الصَّلاَةَ أَرِحْنَا بِهَا ‏"‏ ‏.‏ | F59: Sunan Abi Dawud 4985 | G59: Book 43, Hadith 213 | H59: Sahih (Al-Albani) | I59: https://sunnah.com/abudawud:4985
A60: 59 | B60: Worry, anxiety & distress | C60: Abu Hurairah said; His companion came to him and said; Messenger of Allah! We have thoughts which we cannot dare talk about and we do not like that we have them or talk about them. He said:Have you experienced that? They replied: yes. He said : that is clear faith. | E60: حَدَّثَنَا أَحْمَدُ بْنُ يُونُسَ، حَدَّثَنَا زُهَيْرٌ، حَدَّثَنَا سُهَيْلٌ، عَنْ أَبِيهِ، عَنْ أَبِي هُرَيْرَةَ، قَالَ جَاءَهُ نَاسٌ مِنْ أَصْحَابِهِ فَقَالُوا يَا رَسُولَ اللَّهِ نَجِدُ فِي أَنْفُسِنَا الشَّىْءَ نُعْظِمُ أَنْ نَتَكَلَّمَ بِهِ أَوِ الْكَلاَمَ بِهِ مَا نُحِبُّ أَنَّ لَنَا وَأَنَّا تَكَلَّمْنَا بِهِ ‏.‏ قَالَ ‏"‏ أَوَقَدْ وَجَدْتُمُوهُ ‏"‏ ‏.‏ قَالُوا نَعَمْ ‏.‏ قَالَ ‏"‏ ذَاكَ صَرِيحُ الإِيمَانِ ‏"‏ ‏.‏ | F60: Sunan Abi Dawud 5111 | G60: Book 43, Hadith 339 | H60: Sahih (Al-Albani) | I60: https://sunnah.com/abudawud:5111
A61: 60 | B61: Worry, anxiety & distress | C61: “The Messenger of Allah (ﷺ) taught me some words to say at times of distress: Allah! Allahu Rabbi la ushriku bihi shay’an (Allah, Allah is my Lord, I do not associate anything with Him).” | D61: It was narrated that Asma’ bint ‘Umais said | E61: حَدَّثَنَا أَبُو بَكْرٍ، حَدَّثَنَا مُحَمَّدُ بْنُ بِشْرٍ، ح وَحَدَّثَنَا عَلِيُّ بْنُ مُحَمَّدٍ، حَدَّثَنَا وَكِيعٌ، جَمِيعًا عَنْ عَبْدِ الْعَزِيزِ بْنِ عُمَرَ بْنِ عَبْدِ الْعَزِيزِ، حَدَّثَنِي هِلاَلٌ، مَوْلَى عُمَرَ بْنِ عَبْدِ الْعَزِيزِ عَنْ عُمَرَ بْنِ عَبْدِ الْعَزِيزِ، عَنْ عَبْدِ اللَّهِ بْنِ جَعْفَرٍ، عَنْ أُمِّهِ، أَسْمَاءَ ابْنَةِ عُمَيْسٍ قَالَتْ عَلَّمَنِي رَسُولُ اللَّهِ ـ صلى الله عليه وسلم ـ كَلِمَاتٍ أَقُولُهُنَّ عِنْدَ الْكَرْبِ ‏ "‏ اللَّهُ اللَّهُ رَبِّي لاَ أُشْرِكُ بِهِ شَيْئًا ‏"‏ ‏.‏ | F61: Sunan Ibn Majah 3882 | G61: Book 34, Hadith 56 | H61: Sahih (Al-Albani) | I61: https://sunnah.com/ibnmajah:3882
A62: 61 | B62: Worry, anxiety & distress | C62: “I do not know except that he attributed it to the Prophet (ﷺ)” – “Allah says: ‘O son of Adam, devote yourself to My worship, and I will fill your heart with contentment and take care of your poverty; but if you do not do that, then I will fill your heart with worldly concerns and will not take care of your poverty.’” | D62: (Abu) Khalid Al-Walibi narrated from Abu Hurairah and he (one of the narrators) said | E62: حَدَّثَنَا نَصْرُ بْنُ عَلِيٍّ الْجَهْضَمِيُّ، حَدَّثَنَا عَبْدُ اللَّهِ بْنُ دَاوُدَ، عَنْ عِمْرَانَ بْنِ زَائِدَةَ، عَنْ أَبِيهِ، عَنْ أَبِي خَالِدٍ الْوَالِبِيِّ، عَنْ أَبِي هُرَيْرَةَ، قَالَ - وَلاَ أَعْلَمُهُ إِلاَّ قَدْ رَفَعَهُ - قَالَ ‏ "‏ يَقُولُ اللَّهُ سُبْحَانَهُ يَا ابْنَ آدَمَ تَفَرَّغْ لِعِبَادَتِي أَمْلأْ صَدْرَكَ غِنًى وَأَسُدَّ فَقْرَكَ وَإِنْ لَمْ تَفْعَلْ مَلأْتُ صَدْرَكَ شُغْلاً وَلَمْ أَسُدَّ فَقْرَكَ ‏"‏ ‏.‏ | F62: Sunan Ibn Majah 4107 | G62: Book 37, Hadith 8 | H62: Sahih (Al-Albani) | I62: https://sunnah.com/ibnmajah:4107
A63: 62 | B63: Hope in Allah's mercy | C63: The Prophet (ﷺ) said, "Allah will say to the people of Paradise, "O the people of Paradise!" They will say, 'Labbaik, O our Lord, and Sa`daik, and all the good is in Your Hands!' Allah will say, "Are you satisfied?' They will say, 'Why shouldn't we be satisfied, O our Lord as You have given us what You have not given to any of Your created beings?' He will say, 'Shall I not give you something better than that?' They will say, 'O our Lord! What else could be better than that?' He will say, 'I bestow My Pleasure on you and will never be angry with you after that. | D63: Narrated Abu Sa`id Al-Khudri | E63: حَدَّثَنَا يَحْيَى بْنُ سُلَيْمَانَ، حَدَّثَنِي ابْنُ وَهْبٍ، قَالَ حَدَّثَنِي مَالِكٌ، عَنْ زَيْدِ بْنِ أَسْلَمَ، عَنْ عَطَاءِ بْنِ يَسَارٍ، عَنْ أَبِي سَعِيدٍ الْخُدْرِيِّ ـ رضى الله عنه ـ قَالَ قَالَ النَّبِيُّ صلى الله عليه وسلم ‏ "‏ إِنَّ اللَّهَ يَقُولُ لأَهْلِ الْجَنَّةِ يَا أَهْلَ الْجَنَّةِ‏.‏ فَيَقُولُونَ لَبَّيْكَ رَبَّنَا وَسَعْدَيْكَ وَالْخَيْرُ فِي يَدَيْكَ‏.‏ فَيَقُولُ هَلْ رَضِيتُمْ فَيَقُولُونَ وَمَا لَنَا لاَ نَرْضَى يَا رَبِّ وَقَدْ أَعْطَيْتَنَا مَا لَمْ تُعْطِ أَحَدًا مِنْ خَلْقِكَ‏.‏ فَيَقُولُ أَلاَ أُعْطِيكُمْ أَفْضَلَ مِنْ ذَلِكَ‏.‏ فَيَقُولُونَ يَا رَبِّ وَأَىُّ شَىْءٍ أَفْضَلُ مِنْ ذَلِكَ فَيَقُولُ أُحِلُّ عَلَيْكُمْ رِضْوَانِي فَلاَ أَسْخَطُ عَلَيْكُمْ بَعْدَهُ أَبَدًا ‏"‏‏.‏ | F63: Sahih al-Bukhari 7518 | G63: Book 97, Hadith 143 | H63: Sahih | I63: https://sunnah.com/bukhari:7518
A64: 63 | B64: Hope in Allah's mercy | C64: The Prophet (ﷺ) said: "Whoever loves to meet Allah, Allah loves to meet him; and whoever hates to meet Allah, Allah hates to meet him" | D64: Narrated Abu Musa | E64: حَدَّثَنِي مُحَمَّدُ بْنُ الْعَلاَءِ، حَدَّثَنَا أَبُو أُسَامَةَ، عَنْ بُرَيْدٍ، عَنْ أَبِي بُرْدَةَ، عَنْ أَبِي مُوسَى، عَنِ النَّبِيِّ صلى الله عليه وسلم قَالَ ‏ "‏ مَنْ أَحَبَّ لِقَاءَ اللَّهِ أَحَبَّ اللَّهُ لِقَاءَهُ، وَمَنْ كَرِهَ لِقَاءَ اللَّهِ كَرِهَ اللَّهُ لِقَاءَهُ ‏"‏‏.‏ | F64: Sahih al-Bukhari 6508 | G64: Book 81, Hadith 97 | H64: Sahih | I64: https://sunnah.com/bukhari:6508
A65: 64 | B65: Hope in Allah's mercy | C65: The Prophet (ﷺ) said, "Allah says: 'I am just as My slave thinks I am, (i.e. I am able to do for him what he thinks I can do for him) and I am with him if He remembers Me. If he remembers Me in himself, I too, remember him in Myself; and if he remembers Me in a group of people, I remember him in a group that is better than they; and if he comes one span nearer to Me, I go one cubit nearer to him; and if he comes one cubit nearer to Me, I go a distance of two outstretched arms nearer to him; and if he comes to Me walking, I go to him running" | D65: Narrated Abu Huraira | E65: حَدَّثَنَا عُمَرُ بْنُ حَفْصٍ، حَدَّثَنَا أَبِي، حَدَّثَنَا الأَعْمَشُ، سَمِعْتُ أَبَا صَالِحٍ، عَنْ أَبِي هُرَيْرَةَ ـ رضى الله عنه ـ قَالَ قَالَ النَّبِيُّ صلى الله عليه وسلم ‏ "‏ يَقُولُ اللَّهُ تَعَالَى أَنَا عِنْدَ ظَنِّ عَبْدِي بِي، وَأَنَا مَعَهُ إِذَا ذَكَرَنِي، فَإِنْ ذَكَرَنِي فِي نَفْسِهِ ذَكَرْتُهُ فِي نَفْسِي، وَإِنْ ذَكَرَنِي فِي مَلأٍ ذَكَرْتُهُ فِي مَلأٍ خَيْرٍ مِنْهُمْ، وَإِنْ تَقَرَّبَ إِلَىَّ بِشِبْرٍ تَقَرَّبْتُ إِلَيْهِ ذِرَاعًا، وَإِنْ تَقَرَّبَ إِلَىَّ ذِرَاعًا تَقَرَّبْتُ إِلَيْهِ بَاعًا، وَإِنْ أَتَانِي يَمْشِي أَتَيْتُهُ هَرْوَلَةً ‏"‏‏.‏ | F65: Sahih al-Bukhari 7405 | G65: Book 97, Hadith 34 | H65: Sahih | I65: https://sunnah.com/bukhari:7405
A66: 65 | B66: Hope in Allah's mercy | C66: I heard Allah's Messenger (ﷺ) saying, Allah divided Mercy into one hundred parts. He kept ninety nine parts with Him and sent down one part to the earth, and because of that, its one single part, His Creations are merciful to each other, so that even the mare lifts up its hoofs away from its baby animal, lest it should trample on it. | D66: Narrated Abu Huraira | E66: حَدَّثَنَا الْحَكَمُ بْنُ نَافِعٍ، أَخْبَرَنَا شُعَيْبٌ، عَنِ الزُّهْرِيِّ، أَخْبَرَنَا سَعِيدُ بْنُ الْمُسَيَّبِ، أَنَّ أَبَا هُرَيْرَةَ، قَالَ سَمِعْتُ رَسُولَ اللَّهِ صلى الله عليه وسلم يَقُولُ ‏ "‏ جَعَلَ اللَّهُ الرَّحْمَةَ مِائَةَ جُزْءٍ، فَأَمْسَكَ عِنْدَهُ تِسْعَةً وَتِسْعِينَ جُزْءًا، وَأَنْزَلَ فِي الأَرْضِ جُزْءًا وَاحِدًا، فَمِنْ ذَلِكَ الْجُزْءِ يَتَرَاحَمُ الْخَلْقُ، حَتَّى تَرْفَعَ الْفَرَسُ حَافِرَهَا عَنْ وَلَدِهَا خَشْيَةَ أَنْ تُصِيبَهُ ‏"‏‏.‏ | F66: Sahih al-Bukhari 6000 | G66: Book 78, Hadith 31 | H66: Sahih | I66: https://sunnah.com/bukhari:6000
A67: 66 | B67: Hope in Allah's mercy | C67: The Prophet (ﷺ) said, "My Lord says, 'If My slave comes nearer to me for a span, I go nearer to him for a cubit; and if he comes nearer to Me for a cubit, I go nearer to him for the span of outstretched arms; and if he comes to Me walking, I go to him running" | D67: Narrated Anas | E67: حَدَّثَنِي مُحَمَّدُ بْنُ عَبْدِ الرَّحِيمِ، حَدَّثَنَا أَبُو زَيْدٍ، سَعِيدُ بْنُ الرَّبِيعِ الْهَرَوِيُّ حَدَّثَنَا شُعْبَةُ، عَنْ قَتَادَةَ، عَنْ أَنَسٍ ـ رضى الله عنه ـ عَنِ النَّبِيِّ صلى الله عليه وسلم يَرْوِيهِ عَنْ رَبِّهِ، قَالَ ‏ "‏ إِذَا تَقَرَّبَ الْعَبْدُ إِلَىَّ شِبْرًا تَقَرَّبْتُ إِلَيْهِ ذِرَاعًا، وَإِذَا تَقَرَّبَ مِنِّي ذِرَاعًا تَقَرَّبْتُ مِنْهُ بَاعًا، وَإِذَا أَتَانِي مَشْيًا أَتَيْتُهُ هَرْوَلَةً ‏"‏‏.‏ | F67: Sahih al-Bukhari 7536 | G67: Book 97, Hadith 161 | H67: Sahih | I67: https://sunnah.com/bukhari:7536
A68: 67 | B68: Hope in Allah's mercy | C68: The Prophet (ﷺ) said, "If Allah loves a person, He calls Gabriel saying, 'Allah loves so and-so; O Gabriel! Love him.' Gabriel would love him and make an announcement amongst the inhabitants of the Heaven. 'Allah loves so-and-so, therefore you should love him also,' and so all the inhabitants of the Heaven would love him, and then he is granted the pleasure of the people on the earth" | D68: Narrated Abu Huraira | E68: حَدَّثَنَا مُحَمَّدُ بْنُ سَلاَمٍ، أَخْبَرَنَا مَخْلَدٌ، أَخْبَرَنَا ابْنُ جُرَيْجٍ، قَالَ أَخْبَرَنِي مُوسَى بْنُ عُقْبَةَ، عَنْ نَافِعٍ، قَالَ قَالَ أَبُو هُرَيْرَةَ ـ رضى الله عنه ـ عَنِ النَّبِيِّ صلى الله عليه وسلم‏.‏ وَتَابَعَهُ أَبُو عَاصِمٍ عَنِ ابْنِ جُرَيْجٍ، قَالَ أَخْبَرَنِي مُوسَى بْنُ عُقْبَةَ، عَنْ نَافِعٍ، عَنْ أَبِي هُرَيْرَةَ، عَنِ النَّبِيِّ صلى الله عليه وسلم قَالَ ‏ "‏ إِذَا أَحَبَّ اللَّهُ الْعَبْدَ نَادَى جِبْرِيلَ إِنَّ اللَّهَ يُحِبُّ فُلاَنًا فَأَحْبِبْهُ‏.‏ فَيُحِبُّهُ جِبْرِيلُ، فَيُنَادِي جِبْرِيلُ فِي أَهْلِ السَّمَاءِ إِنَّ اللَّهَ يُحِبُّ فُلاَنًا فَأَحِبُّوهُ‏.‏ فَيُحِبُّهُ أَهْلُ السَّمَاءِ، ثُمَّ يُوضَعُ لَهُ الْقَبُولُ فِي الأَرْضِ ‏"‏‏.‏ | F68: Sahih al-Bukhari 3209 | G68: Book 59, Hadith 20 | H68: Sahih | I68: https://sunnah.com/bukhari:3209
A69: 68 | B69: Hope in Allah's mercy | C69: Allah's Messenger (ﷺ) said, "A prostitute was forgiven by Allah, because, passing by a panting dog near a well and seeing that the dog was about to die of thirst, she took off her shoe, and tying it with her head-cover she drew out some water for it. So, Allah forgave her because of that" | D69: Narrated Abu Huraira | E69: حَدَّثَنَا الْحَسَنُ بْنُ الصَّبَّاحِ، حَدَّثَنَا إِسْحَاقُ الأَزْرَقُ، حَدَّثَنَا عَوْفٌ، عَنِ الْحَسَنِ، وَابْنِ، سِيرِينَ عَنْ أَبِي هُرَيْرَةَ ـ رضى الله عنه ـ عَنْ رَسُولِ اللَّهِ صلى الله عليه وسلم قَالَ ‏ "‏ غُفِرَ لاِمْرَأَةٍ مُومِسَةٍ مَرَّتْ بِكَلْبٍ عَلَى رَأْسِ رَكِيٍّ يَلْهَثُ، قَالَ كَادَ يَقْتُلُهُ الْعَطَشُ، فَنَزَعَتْ خُفَّهَا، فَأَوْثَقَتْهُ بِخِمَارِهَا، فَنَزَعَتْ لَهُ مِنَ الْمَاءِ، فَغُفِرَ لَهَا بِذَلِكَ ‏"‏‏.‏ | F69: Sahih al-Bukhari 3321 | G69: Book 59, Hadith 127 | H69: Sahih | I69: https://sunnah.com/bukhari:3321
A70: 69 | B70: Hope in Allah's mercy | C70: Allah's Messenger (ﷺ) said, "Allah said, 'I will declare war against him who shows hostility to a pious worshipper of Mine. And the most beloved things with which My slave comes nearer to Me, is what I have enjoined upon him; and My slave keeps on coming closer to Me through performing Nawafil (praying or doing extra deeds besides what is obligatory) till I love him, so I become his sense of hearing with which he hears, and his sense of sight with which he sees, and his hand with which he grips, and his leg with which he walks; and if he asks Me, I will give him, and if he asks My protection (Refuge), I will protect him; (i.e. give him My Refuge) and I do not hesitate to do anything as I hesitate to take the soul of the believer, for he hates death, and I hate to disappoint him" | D70: Narrated Abu Huraira | E70: حَدَّثَنِي مُحَمَّدُ بْنُ عُثْمَانَ، حَدَّثَنَا خَالِدُ بْنُ مَخْلَدٍ، حَدَّثَنَا سُلَيْمَانُ بْنُ بِلاَلٍ، حَدَّثَنِي شَرِيكُ بْنُ عَبْدِ اللَّهِ بْنِ أَبِي نَمِرٍ، عَنْ عَطَاءٍ، عَنْ أَبِي هُرَيْرَةَ، قَالَ قَالَ رَسُولُ اللَّهِ صلى الله عليه وسلم ‏ "‏ إِنَّ اللَّهَ قَالَ مَنْ عَادَى لِي وَلِيًّا فَقَدْ آذَنْتُهُ بِالْحَرْبِ، وَمَا تَقَرَّبَ إِلَىَّ عَبْدِي بِشَىْءٍ أَحَبَّ إِلَىَّ مِمَّا افْتَرَضْتُ عَلَيْهِ، وَمَا يَزَالُ عَبْدِي يَتَقَرَّبُ إِلَىَّ بِالنَّوَافِلِ حَتَّى أُحِبَّهُ، فَإِذَا أَحْبَبْتُهُ كُنْتُ سَمْعَهُ الَّذِي يَسْمَعُ بِهِ، وَبَصَرَهُ الَّذِي يُبْصِرُ بِهِ، وَيَدَهُ الَّتِي يَبْطُشُ بِهَا وَرِجْلَهُ الَّتِي يَمْشِي بِهَا، وَإِنْ سَأَلَنِي لأُعْطِيَنَّهُ، وَلَئِنِ اسْتَعَاذَنِي لأُعِيذَنَّهُ، وَمَا تَرَدَّدْتُ عَنْ شَىْءٍ أَنَا فَاعِلُهُ تَرَدُّدِي عَنْ نَفْسِ الْمُؤْمِنِ، يَكْرَهُ الْمَوْتَ وَأَنَا أَكْرَهُ مَسَاءَتَهُ ‏"‏‏.‏ | F70: Sahih al-Bukhari 6502 | G70: Book 81, Hadith 91 | H70: Sahih | I70: https://sunnah.com/bukhari:6502
A71: 70 | B71: Hope in Allah's mercy | C71: The Prophet (ﷺ) narrating about his Lord I'm and said, "Allah ordered (the appointed angels over you) that the good and the bad deeds be written, and He then showed (the way) how (to write). If somebody intends to do a good deed and he does not do it, then Allah will write for him a full good deed (in his account with Him); and if he intends to do a good deed and actually did it, then Allah will write for him (in his account) with Him (its reward equal) from ten to seven hundred times to many more times: and if somebody intended to do a bad deed and he does not do it, then Allah will write a full good deed (in his account) with Him, and if he intended to do it (a bad deed) and actually did it, then Allah will write one bad deed (in his account)" | D71: Narrated Ibn `Abbas | E71: حَدَّثَنَا أَبُو مَعْمَرٍ، حَدَّثَنَا عَبْدُ الْوَارِثِ، حَدَّثَنَا جَعْدٌ أَبُو عُثْمَانَ، حَدَّثَنَا أَبُو رَجَاءٍ الْعُطَارِدِيُّ، عَنِ ابْنِ عَبَّاسٍ ـ رضى الله عنهما ـ عَنِ النَّبِيِّ صلى الله عليه وسلم فِيمَا يَرْوِي عَنْ رَبِّهِ عَزَّ وَجَلَّ قَالَ قَالَ ‏ "‏ إِنَّ اللَّهَ كَتَبَ الْحَسَنَاتِ وَالسَّيِّئَاتِ، ثُمَّ بَيَّنَ ذَلِكَ فَمَنْ هَمَّ بِحَسَنَةٍ فَلَمْ يَعْمَلْهَا كَتَبَهَا اللَّهُ لَهُ عِنْدَهُ حَسَنَةً كَامِلَةً، فَإِنْ هُوَ هَمَّ بِهَا فَعَمِلَهَا كَتَبَهَا اللَّهُ لَهُ عِنْدَهُ عَشْرَ حَسَنَاتٍ إِلَى سَبْعِمِائَةِ ضِعْفٍ إِلَى أَضْعَافٍ كَثِيرَةٍ، وَمَنْ هَمَّ بِسَيِّئَةٍ فَلَمْ يَعْمَلْهَا كَتَبَهَا اللَّهُ لَهُ عِنْدَهُ حَسَنَةً كَامِلَةً، فَإِنْ هُوَ هَمَّ بِهَا فَعَمِلَهَا كَتَبَهَا اللَّهُ لَهُ سَيِّئَةً وَاحِدَةً ‏"‏‏.‏ | F71: Sahih al-Bukhari 6491 | G71: Book 81, Hadith 80 | H71: Sahih | I71: https://sunnah.com/bukhari:6491
A72: 71 | B72: Hope in Allah's mercy | C72: Allah's Messenger (ﷺ) stood up for the prayer and we too stood up along with him. Then a bedouin shouted while offering prayer. "O Allah! Bestow Your Mercy on me and Muhammad only and do not bestow it on anybody else along with us." When the Prophet (ﷺ) had finished his prayer with Taslim, he said to the Bedouin, "You have limited (narrowed) a very vast (thing)," meaning Allah's Mercy. | D72: Narrated Abu Huraira | E72: حَدَّثَنَا أَبُو الْيَمَانِ، أَخْبَرَنَا شُعَيْبٌ، عَنِ الزُّهْرِيِّ، قَالَ أَخْبَرَنِي أَبُو سَلَمَةَ بْنُ عَبْدِ الرَّحْمَنِ، أَنَّ أَبَا هُرَيْرَةَ، قَالَ قَامَ رَسُولُ اللَّهِ صلى الله عليه وسلم فِي صَلاَةٍ وَقُمْنَا مَعَهُ، فَقَالَ أَعْرَابِيٌّ وَهْوَ فِي الصَّلاَةِ اللَّهُمَّ ارْحَمْنِي وَمُحَمَّدًا، وَلاَ تَرْحَمْ مَعَنَا أَحَدًا‏.‏ فَلَمَّا سَلَّمَ النَّبِيُّ صلى الله عليه وسلم قَالَ لِلأَعْرَابِيِّ ‏ "‏ لَقَدْ حَجَّرْتَ وَاسِعًا ‏"‏‏.‏ يُرِيدُ رَحْمَةَ اللَّهِ‏.‏ | F72: Sahih al-Bukhari 6010 | G72: Book 78, Hadith 41 | H72: Sahih | I72: https://sunnah.com/bukhari:6010
... A80: 79 | B80: Hope in Allah's mercy | C80: Allah would not forgive such and such (person). Thereupon Allah the Exalted and Glorious, said: Who is he who adjures about Me that I would not grant pardon to so and so; I have granted pardon to so and so and blotted out his deeds (who took an oath that I would not grant pardon to him) | D80: Jundub reported that Allah's Messenger (ﷺ) stated that a person said | E80: حَدَّثَنَا سُوَيْدُ بْنُ سَعِيدٍ، عَنْ مُعْتَمِرِ بْنِ سُلَيْمَانَ، عَنْ أَبِيهِ، حَدَّثَنَا أَبُو عِمْرَانَ الْجَوْنِيُّ، عَنْ جُنْدَبٍ، أَنَّ رَسُولَ اللَّهِ صلى الله عليه وسلم حَدَّثَ ‏ "‏ أَنَّ رَجُلاً قَالَ وَاللَّهِ لاَ يَغْفِرُ اللَّهُ لِفُلاَنٍ وَإِنَّ اللَّهَ تَعَالَى قَالَ مَنْ ذَا الَّذِي يَتَأَلَّى عَلَىَّ أَنْ لاَ أَغْفِرَ لِفُلاَنٍ فَإِنِّي قَدْ غَفَرْتُ لِفُلاَنٍ وَأَحْبَطْتُ عَمَلَكَ ‏"‏ ‏.‏ أَوْ كَمَا قَالَ ‏.‏ | F80: Sahih Muslim 2621 | G80: Book 45, Hadith 178 | H80: Sahih | I80: https://sunnah.com/muslim:2621
A81: 80 | B81: Hope in Allah's mercy | C81: Umar b. Khattab reported that there were brought some prisoners to Allah's Messenger (ﷺ) amongst whom there was also a woman, who was searching (for someone) and when she found a child amongst the prisoners, she took hold of it, pressed it against her chest and provided it suck. Thereupon Allah's Messenger (ﷺ) said:Do you think this woman would ever afford to throw her child in the Fire? We said: By Allah, so far as it lies in her power, she would never throw the child in Fire. ' Thereupon Allah's Messenger (ﷺ) said: Allah is more kind to His servants than this woman is to her child. | E81: حَدَّثَنِي الْحَسَنُ بْنُ عَلِيٍّ الْحُلْوَانِيُّ، وَمُحَمَّدُ بْنُ سَهْلٍ التَّمِيمِيُّ، - وَاللَّفْظُ لِحَسَنٍ - حَدَّثَنَا ابْنُ أَبِي مَرْيَمَ، حَدَّثَنَا أَبُو غَسَّانَ، حَدَّثَنِي زَيْدُ بْنُ أَسْلَمَ، عَنْ أَبِيهِ، عَنْ عُمَرَ بْنِ الْخَطَّابِ، أَنَّهُ قَالَ قَدِمَ عَلَى رَسُولِ اللَّهِ صلى الله عليه وسلم بِسَبْىٍ فَإِذَا امْرَأَةٌ مِنَ السَّبْىِ تَبْتَغِي إِذَا وَجَدَتْ صَبِيًّا فِي السَّبْىِ أَخَذَتْهُ فَأَلْصَقَتْهُ بِبَطْنِهَا وَأَرْضَعَتْهُ فَقَالَ لَنَا رَسُولُ اللَّهِ صلى الله عليه وسلم ‏"‏ أَتَرَوْنَ هَذِهِ الْمَرْأَةَ طَارِحَةً وَلَدَهَا فِي النَّارِ ‏"‏ ‏.‏ قُلْنَا لاَ وَاللَّهِ وَهِيَ تَقْدِرُ عَلَى أَنْ لاَ تَطْرَحَهُ ‏.‏ فَقَالَ رَسُولُ اللَّهِ صلى الله عليه وسلم ‏"‏ لَلَّهُ أَرْحَمُ بِعِبَادِهِ مِنْ هَذِهِ بِوَلَدِهَا ‏"‏ ‏.‏ | F81: Sahih Muslim 2754 | G81: Book 50, Hadith 26 | H81: Sahih | I81: https://sunnah.com/muslim:2754
A82: 81 | B82: Hope in Allah's mercy | C82: “Allah, Blessed is He and Most High, said: ‘O son of Adam! Verily as long as you called upon Me and hoped in Me, I forgave you, despite whatever may have occurred from you, and I did not mind. O son of Adam! Were your sins to reach the clouds of the sky, then you sought forgiveness from Me, I would forgive you, and I would not mind. So son of Adam! If you came to me with sins nearly as great as the earth, and then you met Me not associating anything with Me, I would come to you with forgiveness nearly as great as it.’” | D82: Anas bin Malik narrated that the Messenger of Allah (ﷺ) said | E82: حَدَّثَنَا عَبْدُ اللَّهِ بْنُ إِسْحَاقَ الْجَوْهَرِيُّ الْبَصْرِيُّ، حَدَّثَنَا أَبُو عَاصِمٍ، حَدَّثَنَا كَثِيرُ بْنُ فَائِدٍ، حَدَّثَنَا سَعِيدُ بْنُ عُبَيْدٍ، قَالَ سَمِعْتُ بَكْرَ بْنَ عَبْدِ اللَّهِ الْمُزَنِيَّ، يَقُولُ حَدَّثَنَا أَنَسُ بْنُ مَالِكٍ، قَالَ سَمِعْتُ رَسُولَ اللَّهِ صلى الله عليه وسلم يَقُولُ ‏ "‏ قَالَ اللَّهُ يَا ابْنَ آدَمَ إِنَّكَ مَا دَعَوْتَنِي وَرَجَوْتَنِي غَفَرْتُ لَكَ عَلَى مَا كَانَ فِيكَ وَلاَ أُبَالِي يَا ابْنَ آدَمَ لَوْ بَلَغَتْ ذُنُوبُكَ عَنَانَ السَّمَاءِ ثُمَّ اسْتَغْفَرْتَنِي غَفَرْتُ لَكَ وَلاَ أُبَالِي يَا ابْنَ آدَمَ إِنَّكَ لَوْ أَتَيْتَنِي بِقُرَابِ الأَرْضِ خَطَايَا ثُمَّ لَقِيتَنِي لاَ تُشْرِكُ بِي شَيْئًا لأَتَيْتُكَ بِقُرَابِهَا مَغْفِرَةً ‏"‏ ‏.‏ قَالَ أَبُو عِيسَى هَذَا حَدِيثٌ غَرِيبٌ لاَ نَعْرِفُهُ إِلاَّ مِنْ هَذَا الْوَجْهِ ‏.‏ | F82: Jami' at-Tirmidhi 3540 | G82: Book 48, Hadith 171 | H82: Sahih (Al-Albani) | I82: https://sunnah.com/tirmidhi:3540
A83: 82 | B83: Hope in Allah's mercy | C83: When Allah wants good for a slave, He puts him in action." It was said: "How does he put him in action O Messenger Of Allah?" He said: "By making him meet up with the righteous deeds before death. | D83: Anas narrated that the Messenger of Allah (s.a.w) said | E83: حَدَّثَنَا عَلِيُّ بْنُ حُجْرٍ، قال: حَدَّثَنَا إِسْمَاعِيلُ بْنُ جَعْفَرٍ، عَنْ حُمَيْدٍ، عَنْ أَنَسٍ، قَالَ قَالَ رَسُولُ اللَّهِ صلى الله عليه وسلم ‏"‏ إِذَا أَرَادَ اللَّهُ بِعَبْدٍ خَيْرًا اسْتَعْمَلَهُ ‏"‏ ‏.‏ فَقِيلَ كَيْفَ يَسْتَعْمِلُهُ يَا رَسُولَ اللَّهِ قَالَ ‏"‏ يُوَفِّقُهُ لِعَمَلٍ صَالِحٍ قَبْلَ الْمَوْتِ ‏"‏ ‏.‏ قَالَ أَبُو عِيسَى هَذَا حَدِيثٌ حَسَنٌ صَحِيحٌ ‏.‏ | F83: Jami' at-Tirmidhi 2142 | G83: Book 32, Hadith 10 | H83: Sahih (Al-Albani) | I83: https://sunnah.com/tirmidhi:2142
A84: 83 | B84: Hope in Allah's mercy | C84: “I said to the Prophet (ﷺ): ‘(What do you say about when) a man does a deed for the sake of Allah, and people love him for it?’ He said: ‘That is the immediate glad tidings of the believer.’” | D84: It was narrated from Abu Dharr | E84: حَدَّثَنَا مُحَمَّدُ بْنُ بَشَّارٍ، حَدَّثَنَا مُحَمَّدُ بْنُ جَعْفَرٍ، حَدَّثَنَا شُعْبَةُ، عَنْ أَبِي عِمْرَانَ الْجَوْنِيِّ، عَنْ عَبْدِ اللَّهِ بْنِ الصَّامِتِ، عَنْ أَبِي ذَرٍّ، عَنِ النَّبِيِّ ـ صلى الله عليه وسلم ـ قَالَ قُلْتُ لَهُ ‏:‏ الرَّجُلُ يَعْمَلُ الْعَمَلَ لِلَّهِ فَيُحِبُّهُ النَّاسُ عَلَيْهِ قَالَ ‏:‏ ‏ "‏ ذَلِكَ عَاجِلُ بُشْرَى الْمُؤْمِنِ ‏"‏ ‏.‏ | F84: Sunan Ibn Majah 4225 | G84: Book 37, Hadith 126 | H84: Sahih (Al-Albani) | I84: https://sunnah.com/ibnmajah:4225
A85: 84 | B85: Hope in Allah's mercy | C85: It was narrated from Anas that the Prophet (ﷺ) entered upon a young man who was dying and said:“How do you feel?” He said: “I have hope in Allah, O Messenger of Allah, but I fear my sins.” The Messenger of Allah (ﷺ) said: “These two things (hope and fear) do not coexist in the heart of a person in a situation like this, but Allah will give him that which he hopes for and keep him safe from that which he fears.” | E85: حَدَّثَنَا عَبْدُ اللَّهِ بْنُ الْحَكَمِ بْنِ أَبِي زِيَادٍ، حَدَّثَنَا سَيَّارٌ، حَدَّثَنَا جَعْفَرٌ، عَنْ ثَابِتٍ، عَنْ أَنَسٍ، ‏:‏ أَنَّ النَّبِيَّ ـ صلى الله عليه وسلم ـ دَخَلَ عَلَى شَابٍّ وَهُوَ فِي الْمَوْتِ فَقَالَ ‏:‏ ‏"‏ كَيْفَ تَجِدُكَ ‏"‏ ‏.‏ قَالَ ‏:‏ أَرْجُو اللَّهَ يَا رَسُولَ اللَّهِ وَأَخَافُ ذُنُوبِي ‏.‏ فَقَالَ رَسُولُ اللَّهِ ـ صلى الله عليه وسلم ـ ‏:‏ ‏"‏ لاَ يَجْتَمِعَانِ فِي قَلْبِ عَبْدٍ فِي مِثْلِ هَذَا الْمَوْطِنِ إِلاَّ أَعْطَاهُ اللَّهُ مَا يَرْجُو وَآمَنَهُ مِمَّا يَخَافُ ‏"‏ ‏.‏ | F85: Sunan Ibn Majah 4261 | G85: Book 37, Hadith 162 | H85: Hasan (Al-Albani) | I85: https://sunnah.com/ibnmajah:4261
A86: 85 | B86: Hope in Allah's mercy | C86: There is no good deed that the son of Adam does, but between ten and seven hundred Hasanahs will be recorded for him. Allah, the mighty and sublime, said: 'Except fasing, for it is for me and I shall reward for it. He gives up his desires and his food for my sake. Fasting is a shield, and the fasting person has two moments of joy. One when he breaks his fast and another when he meets his Lord. And the smell that comes from the mouth of the fasting person is better before Allah than the fragrance of musk. | D86: It was narrated from Abu Hurairah that the Messenger of Allah said | E86: أَخْبَرَنَا إِسْحَاقُ بْنُ إِبْرَاهِيمَ، قَالَ أَنْبَأَنَا جَرِيرٌ، عَنِ الأَعْمَشِ، عَنْ أَبِي صَالِحٍ، عَنْ أَبِي هُرَيْرَةَ، عَنْ رَسُولِ اللَّهِ صلى الله عليه وسلم قَالَ ‏ "‏ مَا مِنْ حَسَنَةٍ عَمِلَهَا ابْنُ آدَمَ إِلاَّ كُتِبَ لَهُ عَشْرُ حَسَنَاتٍ إِلَى سَبْعِمِائَةِ ضِعْفٍ قَالَ اللَّهُ عَزَّ وَجَلَّ إِلاَّ الصِّيَامَ فَإِنَّهُ لِي وَأَنَا أَجْزِي بِهِ يَدَعُ شَهْوَتَهُ وَطَعَامَهُ مِنْ أَجْلِي الصِّيَامُ جُنَّةٌ لِلصَّائِمِ فَرْحَتَانِ فَرْحَةٌ عِنْدَ فِطْرِهِ وَفَرْحَةٌ عِنْدَ لِقَاءِ رَبِّهِ وَلَخُلُوفُ فَمِ الصَّائِمِ أَطْيَبُ عِنْدَ اللَّهِ مِنْ رِيحِ الْمِسْكِ ‏"‏ ‏.‏ | F86: Sunan an-Nasa'i 2215 | G86: Book 22, Hadith 126 | H86: Sahih (Al-Albani) | I86: https://sunnah.com/nasai:2215
A87: 86 | B87: Repentance & forgiveness of sins | C87: Abu Bakr As-Siddiq said to the Prophet (ﷺ) "O Allah's Messenger (ﷺ)! Teach me an invocation with which I may invoke Allah in my prayers." The Prophet (ﷺ) said, "Say: O Allah! I have wronged my soul very much (oppressed myself), and none forgives the sins but You; so please bestow Your Forgiveness upon me. No doubt, You are the Oft-Forgiving, Most Merciful" | D87: Narrated `Abdullah bin `Amr | E87: حَدَّثَنَا يَحْيَى بْنُ سُلَيْمَانَ، حَدَّثَنِي ابْنُ وَهْبٍ، أَخْبَرَنِي عَمْرٌو، عَنْ يَزِيدَ، عَنْ أَبِي الْخَيْرِ، سَمِعَ عَبْدَ اللَّهِ بْنَ عَمْرٍو، أَنَّ أَبَا بَكْرٍ الصِّدِّيقَ ـ رضى الله عنه ـ قَالَ لِلنَّبِيِّ صلى الله عليه وسلم يَا رَسُولَ اللَّهِ عَلِّمْنِي دُعَاءً أَدْعُو بِهِ فِي صَلاَتِي‏.‏ قَالَ ‏ "‏ قُلِ اللَّهُمَّ إِنِّي ظَلَمْتُ نَفْسِي ظُلْمًا كَثِيرًا، وَلاَ يَغْفِرُ الذُّنُوبَ إِلاَّ أَنْتَ، فَاغْفِرْ لِي مِنْ عِنْدِكَ مَغْفِرَةً، إِنَّكَ أَنْتَ الْغَفُورُ الرَّحِيمُ ‏"‏‏.‏ | F87: Sahih al-Bukhari 7387 | H87: Sahih | I87: https://sunnah.com/bukhari:7387
A88: 87 | B88: Repentance & forgiveness of sins | C88: I heard Allah's Messenger (ﷺ) saying." By Allah! I ask for forgiveness from Allah and turn to Him in repentance more than seventy times a day" | D88: Narrated Abu Huraira | E88: حَدَّثَنَا أَبُو الْيَمَانِ، أَخْبَرَنَا شُعَيْبٌ، عَنِ الزُّهْرِيِّ، قَالَ أَخْبَرَنِي أَبُو سَلَمَةَ بْنُ عَبْدِ الرَّحْمَنِ، قَالَ قَالَ أَبُو هُرَيْرَةَ سَمِعْتُ رَسُولَ اللَّهِ صلى الله عليه وسلم يَقُولُ ‏ "‏ وَاللَّهِ إِنِّي لأَسْتَغْفِرُ اللَّهَ وَأَتُوبُ إِلَيْهِ فِي الْيَوْمِ أَكْثَرَ مِنْ سَبْعِينَ مَرَّةً ‏"‏‏.‏ | F88: Sahih al-Bukhari 6307 | G88: Book 80, Hadith 4 | H88: Sahih | I88: https://sunnah.com/bukhari:6307
A89: 88 | B89: Repentance & forgiveness of sins | C89: I heard Allah's Messenger (ﷺ) saying. "All the sins of my followers will be forgiven except those of the Mujahirin (those who commit a sin openly or disclose their sins to the people). An example of such disclosure is that a person commits a sin at night and though Allah screens it from the public, then he comes in the morning, and says, 'O so-and-so, I did such-and-such (evil) deed yesterday,' though he spent his night screened by his Lord (none knowing about his sin) and in the morning he removes Allah's screen from himself" | D89: Narrated Abu Huraira | E89: حَدَّثَنَا عَبْدُ الْعَزِيزِ بْنُ عَبْدِ اللَّهِ، حَدَّثَنَا إِبْرَاهِيمُ بْنُ سَعْدٍ، عَنِ ابْنِ أَخِي ابْنِ شِهَابٍ، عَنِ ابْنِ شِهَابٍ، عَنْ سَالِمِ بْنِ عَبْدِ اللَّهِ، قَالَ سَمِعْتُ أَبَا هُرَيْرَةَ، يَقُولُ سَمِعْتُ رَسُولَ اللَّهِ صلى الله عليه وسلم يَقُولُ ‏ "‏ كُلُّ أُمَّتِي مُعَافًى إِلاَّ الْمُجَاهِرِينَ، وَإِنَّ مِنَ الْمَجَانَةِ أَنْ يَعْمَلَ الرَّجُلُ بِاللَّيْلِ عَمَلاً، ثُمَّ يُصْبِحَ وَقَدْ سَتَرَهُ اللَّهُ، فَيَقُولَ يَا فُلاَنُ عَمِلْتُ الْبَارِحَةَ كَذَا وَكَذَا، وَقَدْ بَاتَ يَسْتُرُهُ رَبُّهُ وَيُصْبِحُ يَكْشِفُ سِتْرَ اللَّهِ عَنْهُ ‏"‏‏.‏ | F89: Sahih al-Bukhari 6069 | G89: Book 78, Hadith 99 | H89: Sahih | I89: https://sunnah.com/bukhari:6069
A90: 89 | B90: Repentance & forgiveness of sins | C90: A man kissed a woman (unlawfully) and then went to the Prophet (ﷺ) and informed him. Allah revealed: And offer prayers perfectly At the two ends of the day And in some hours of the night (i.e. the five compulsory prayers). Verily! good deeds remove (annul) the evil deeds (small sins) (11.114). The man asked Allah's Messenger (ﷺ), "Is it for me?" He said, "It is for all my followers" | D90: Narrated Ibn Mas`ud | E90: حَدَّثَنَا قُتَيْبَةُ، قَالَ حَدَّثَنَا يَزِيدُ بْنُ زُرَيْعٍ، عَنْ سُلَيْمَانَ التَّيْمِيِّ، عَنْ أَبِي عُثْمَانَ النَّهْدِيِّ، عَنِ ابْنِ مَسْعُودٍ، أَنَّ رَجُلاً، أَصَابَ مِنَ امْرَأَةٍ قُبْلَةً، فَأَتَى النَّبِيَّ صلى الله عليه وسلم فَأَخْبَرَهُ، فَأَنْزَلَ اللَّهُ ‏{‏أَقِمِ الصَّلاَةَ طَرَفَىِ النَّهَارِ وَزُلَفًا مِنَ اللَّيْلِ إِنَّ الْحَسَنَاتِ يُذْهِبْنَ السَّيِّئَاتِ‏}‏‏.‏ فَقَالَ الرَّجُلُ يَا رَسُولَ اللَّهِ أَلِي هَذَا قَالَ ‏"‏ لِجَمِيعِ أُمَّتِي كُلِّهِمْ ‏"‏‏.‏ | F90: Sahih al-Bukhari 526 | G90: Book 9, Hadith 5 | H90: Sahih | I90: https://sunnah.com/bukhari:526
A91: 90 | B91: Repentance & forgiveness of sins | C91: Allah's Messenger (ﷺ) said, "Allah is more pleased with the repentance of His slave than anyone of you is pleased with finding his camel which he had lost in the desert" | D91: Narrated Anas bin Malik | E91: حَدَّثَنَا إِسْحَاقُ، أَخْبَرَنَا حَبَّانُ، حَدَّثَنَا هَمَّامٌ، حَدَّثَنَا قَتَادَةُ، حَدَّثَنَا أَنَسُ بْنُ مَالِكٍ، عَنِ النَّبِيِّ صلى الله عليه وسلم‏.‏ وَحَدَّثَنَا هُدْبَةُ، حَدَّثَنَا هَمَّامٌ، حَدَّثَنَا قَتَادَةُ، عَنْ أَنَسٍ ـ رضى الله عنه ـ قَالَ قَالَ رَسُولُ اللَّهِ صلى الله عليه وسلم ‏ "‏ اللَّهُ أَفْرَحُ بِتَوْبَةِ عَبْدِهِ مِنْ أَحَدِكُمْ سَقَطَ عَلَى بَعِيرِهِ، وَقَدْ أَضَلَّهُ فِي أَرْضِ فَلاَةٍ ‏"‏‏.‏ | F91: Sahih al-Bukhari 6309 | G91: Book 80, Hadith 6 | H91: Sahih | I91: https://sunnah.com/bukhari:6309
A92: 91 | B92: Repentance & forgiveness of sins | C92: The Prophet (ﷺ) said "The most superior way of asking for forgiveness from Allah is: 'Allahumma anta Rabbi la ilaha illa anta, Khalaqtani wa ana `Abduka, wa ana `ala `ahdika wa wa`dika mastata`tu, A`udhu bika min Sharri ma sana`tu, abu'u Laka bini`matika `alaiya, wa abu'u laka bidhanbi faghfir lee fa innahu la yaghfiru adhdhunuba illa anta." The Prophet (ﷺ) added. "If somebody recites it during the day with firm faith in it, and dies on the same day before the evening, he will be from the people of Paradise; and if somebody recites it at night with firm faith in it, and dies before the morning, he will be from the people of Paradise" | D92: Narrated Shaddad bin Aus | E92: حَدَّثَنَا أَبُو مَعْمَرٍ، حَدَّثَنَا عَبْدُ الْوَارِثِ، حَدَّثَنَا الْحُسَيْنُ، حَدَّثَنَا عَبْدُ اللَّهِ بْنُ بُرَيْدَةَ، عَنْ بُشَيْرِ بْنِ كَعْبٍ الْعَدَوِيِّ، قَالَ حَدَّثَنِي شَدَّادُ بْنُ أَوْسٍ ـ رضى الله عنه ـ عَنِ النَّبِيِّ صلى الله عليه وسلم ‏"‏ سَيِّدُ الاِسْتِغْفَارِ أَنْ تَقُولَ اللَّهُمَّ أَنْتَ رَبِّي، لاَ إِلَهَ إِلاَّ أَنْتَ، خَلَقْتَنِي وَأَنَا عَبْدُكَ، وَأَنَا عَلَى عَهْدِكَ وَوَعْدِكَ مَا اسْتَطَعْتُ، أَعُوذُ بِكَ مِنْ شَرِّ مَا صَنَعْتُ، أَبُوءُ لَكَ بِنِعْمَتِكَ عَلَىَّ وَأَبُوءُ لَكَ بِذَنْبِي، فَاغْفِرْ لِي، فَإِنَّهُ لاَ يَغْفِرُ الذُّنُوبَ إِلاَّ أَنْتَ ‏"‏‏.‏ قَالَ ‏"‏ وَمَنْ قَالَهَا مِنَ النَّهَارِ مُوقِنًا بِهَا، فَمَاتَ مِنْ يَوْمِهِ قَبْلَ أَنْ يُمْسِيَ، فَهُوَ مِنْ أَهْلِ الْجَنَّةِ، وَمَنْ قَالَهَا مِنَ اللَّيْلِ وَهْوَ مُوقِنٌ بِهَا، فَمَاتَ قَبْلَ أَنْ يُصْبِحَ، فَهْوَ مِنْ أَهْلِ الْجَنَّةِ ‏"‏‏.‏ | F92: Sahih al-Bukhari 6306 | G92: Book 80, Hadith 3 | H92: Sahih | I92: https://sunnah.com/bukhari:6306
A93: 92 | B93: Repentance & forgiveness of sins | C93: Narrated Al-Harith bin Suwaid:`Abdullah bin Mas`ud related to us two narrations: One from the Prophet (ﷺ) and the other from himself, saying: A believer sees his sins as if he were sitting under a mountain which, he is afraid, may fall on him; whereas the wicked person considers his sins as flies passing over his nose and he just drives them away like this." Abu Shihab (the sub-narrator) moved his hand over his nose in illustration. (Ibn Mas`ud added): Allah's Messenger (ﷺ) said, "Allah is more pleased with the repentance of His slave than a man who encamps at a place where his life is jeopardized, but he has his riding beast carrying his food and water. He then rests his head and sleeps for a short while and wakes to find his riding beast gone. (He starts looking for it) and suffers from severe heat and thirst or what Allah wished (him to suffer from). He then says, 'I will go back to my place.' He returns and sleeps again, and then (getting up), he raises his head to find his riding beast standing beside him. | E93: حَدَّثَنَا أَحْمَدُ بْنُ يُونُسَ، حَدَّثَنَا أَبُو شِهَابٍ، عَنِ الأَعْمَشِ، عَنْ عُمَارَةَ بْنِ عُمَيْرٍ، عَنِ الْحَارِثِ بْنِ سُوَيْدٍ، حَدَّثَنَا عَبْدُ اللَّهِ، حَدِيثَيْنِ أَحَدُهُمَا عَنِ النَّبِيِّ صلى الله عليه وسلم وَالآخَرُ عَنْ نَفْسِهِ، قَالَ ‏"‏ إِنَّ الْمُؤْمِنَ يَرَى ذُنُوبَهُ كَأَنَّهُ قَاعِدٌ تَحْتَ جَبَلٍ يَخَافُ أَنْ يَقَعَ عَلَيْهِ، وَإِنَّ الْفَاجِرَ يَرَى ذُنُوبَهُ كَذُبَابٍ مَرَّ عَلَى أَنْفِهِ ‏"‏‏.‏ فَقَالَ بِهِ هَكَذَا قَالَ أَبُو شِهَابٍ بِيَدِهِ فَوْقَ أَنْفِهِ‏.‏ ثُمَّ قَالَ ‏"‏ لَلَّهُ أَفْرَحُ بِتَوْبَةِ عَبْدِهِ مِنْ رَجُلٍ نَزَلَ مَنْزِلاً، وَبِهِ مَهْلَكَةٌ، وَمَعَهُ رَاحِلَتُهُ عَلَيْهَا طَعَامُهُ وَشَرَابُهُ، فَوَضَعَ رَأْسَهُ فَنَامَ نَوْمَةً، فَاسْتَيْقَظَ وَقَدْ ذَهَبَتْ رَاحِلَتُهُ، حَتَّى اشْتَدَّ عَلَيْهِ الْحَرُّ وَالْعَطَشُ أَوْ مَا شَاءَ اللَّهُ، قَالَ أَرْجِعُ إِلَى مَكَانِي‏.‏ فَرَجَعَ فَنَامَ نَوْمَةً، ثُمَّ رَفَعَ رَأْسَهُ، فَإِذَا رَاحِلَتُهُ عِنْدَهُ ‏"‏‏.‏ تَابَعَهُ أَبُو عَوَانَةَ وَجَرِيرٌ عَنِ الأَعْمَشِ‏.‏ وَقَالَ أَبُو أُسَامَةَ حَدَّثَنَا الأَعْمَشُ حَدَّثَنَا عُمَارَةُ سَمِعْتُ الْحَارِثَ‏.‏ وَقَالَ شُعْبَةُ وَأَبُو مُسْلِمٍ عَنِ الأَعْمَشِ عَنْ إِبْرَاهِيمَ التَّيْمِيِّ عَنِ الْحَارِثِ بْنِ سُوَيْدٍ‏.‏ وَقَالَ أَبُو مُعَاوِيَةَ حَدَّثَنَا الأَعْمَشُ عَنْ عُمَارَةَ عَنِ الأَسْوَدِ عَنْ عَبْدِ اللَّهِ وَعَنْ إِبْرَاهِيمَ التَّيْمِيِّ عَنِ الْحَارِثِ بْنِ سُوَيْدٍ عَنْ عَبْدِ اللَّهِ‏.‏ | F93: Sahih al-Bukhari 6308 | G93: Book 80, Hadith 5 | H93: Sahih | I93: https://sunnah.com/bukhari:6308
A94: 93 | B94: Repentance & forgiveness of sins | C94: Allah's Messenger (ﷺ) said, "Whoever has oppressed another person concerning his reputation or anything else, he should beg him to forgive him before the Day of Resurrection when there will be no money (to compensate for wrong deeds), but if he has good deeds, those good deeds will be taken from him according to his oppression which he has done, and if he has no good deeds, the sins of the oppressed person will be loaded on him" | D94: Narrated Abu Huraira | E94: حَدَّثَنَا آدَمُ بْنُ أَبِي إِيَاسٍ، حَدَّثَنَا ابْنُ أَبِي ذِئْبٍ، حَدَّثَنَا سَعِيدٌ الْمَقْبُرِيُّ، عَنْ أَبِي هُرَيْرَةَ ـ رضى الله عنه ـ قَالَ قَالَ رَسُولُ اللَّهِ صلى الله عليه وسلم ‏ "‏ مَنْ كَانَتْ لَهُ مَظْلَمَةٌ لأَحَدٍ مِنْ عِرْضِهِ أَوْ شَىْءٍ فَلْيَتَحَلَّلْهُ مِنْهُ الْيَوْمَ، قَبْلَ أَنْ لاَ يَكُونَ دِينَارٌ وَلاَ دِرْهَمٌ، إِنْ كَانَ لَهُ عَمَلٌ صَالِحٌ أُخِذَ مِنْهُ بِقَدْرِ مَظْلَمَتِهِ، وَإِنْ لَمْ تَكُنْ لَهُ حَسَنَاتٌ أُخِذَ مِنْ سَيِّئَاتِ صَاحِبِهِ فَحُمِلَ عَلَيْهِ ‏"‏‏.‏ قَالَ أَبُو عَبْدِ اللَّهِ قَالَ إِسْمَاعِيلُ بْنُ أَبِي أُوَيْسٍ إِنَّمَا سُمِّيَ الْمَقْبُرِيَّ لأَنَّهُ كَانَ نَزَلَ نَاحِيَةَ الْمَقَابِرِ‏.‏ قَالَ أَبُو عَبْدِ اللَّهِ وَسَعِيدٌ الْمَقْبُرِيُّ هُوَ مَوْلَى بَنِي لَيْثٍ، وَهُوَ سَعِيدُ بْنُ أَبِي سَعِيدٍ، وَاسْمُ أَبِي سَعِيدٍ كَيْسَانُ‏.‏ | F94: Sahih al-Bukhari 2449 | G94: Book 46, Hadith 10 | H94: Sahih | I94: https://sunnah.com/bukhari:2449
A95: 94 | B95: Repentance & forgiveness of sins | C95: By Him in Whose Hand is my life, if you were not to commit sin, Allah would sweep you out of existence and He would replace (you by) those people who would commit sin and seek forgiveness from Allah, and He would have pardoned them. | D95: Abu Huraira reported Allah's Messenger (ﷺ) having said | E95: حَدَّثَنِي مُحَمَّدُ بْنُ رَافِعٍ، حَدَّثَنَا عَبْدُ الرَّزَّاقِ، أَخْبَرَنَا مَعْمَرٌ، عَنْ جَعْفَرٍ الْجَزَرِيِّ، عَنْ يَزِيدَ بْنِ الأَصَمِّ، عَنْ أَبِي هُرَيْرَةَ، قَالَ قَالَ رَسُولُ اللَّهِ صلى الله عليه وسلم ‏ "‏ وَالَّذِي نَفْسِي بِيَدِهِ لَوْ لَمْ تُذْنِبُوا لَذَهَبَ اللَّهُ بِكُمْ وَلَجَاءَ بِقَوْمٍ يُذْنِبُونَ فَيَسْتَغْفِرُونَ اللَّهَ فَيَغْفِرُ لَهُمْ ‏"‏ ‏.‏ | F95: Sahih Muslim 2749 | G95: Book 50, Hadith 13 | H95: Sahih | I95: https://sunnah.com/muslim:2749
A96: 95 | B96: Repentance & forgiveness of sins | C96: Al-Agharr al-Muzani, who was one amongst the Companions (of the Holy Prophet) reported that Allah's Messenger (ﷺ) said:There is (at times) some sort of shade upon my heart, and I seek forgiveness from Allah a hundred times a day. | E96: حَدَّثَنَا يَحْيَى بْنُ يَحْيَى، وَقُتَيْبَةُ بْنُ سَعِيدٍ، وَأَبُو الرَّبِيعِ الْعَتَكِيُّ، جَمِيعًا عَنْ حَمَّادٍ، قَالَ يَحْيَى أَخْبَرَنَا حَمَّادُ بْنُ زَيْدٍ، عَنْ ثَابِتٍ، عَنْ أَبِي بُرْدَةَ، عَنِ الأَغَرِّ الْمُزَنِيِّ، - وَكَانَتْ لَهُ صُحْبَةٌ - أَنَّ رَسُولَ اللَّهِ صلى الله عليه وسلم قَالَ ‏ "‏ إِنَّهُ لَيُغَانُ عَلَى قَلْبِي وَإِنِّي لأَسْتَغْفِرُ اللَّهَ فِي الْيَوْمِ مِائَةَ مَرَّةٍ ‏"‏ ‏.‏ | F96: Sahih Muslim 2702a | G96: Book 48, Hadith 52 | H96: Sahih | I96: https://sunnah.com/muslim:2702a
A97: 96 | B97: Repentance & forgiveness of sins | C97: Abu Huraira reported from Allah's Messenger (ﷺ) that his Lord, the Exalted and Glorious, thus said. A servant committed a sin and he said:O Allah, forgive me my sins, and Allah (the Exalted and Glorious) said: My servant commited a sin and then he came to realise that he has a Lord Who forgives the sins and takes to account (the sinner) for the sin. He then again committed a sin and said: My Lord, forgive me my sin, and Allah, the Exalted and High, said: My servant committed a sin and then came to realise that he has a Lord Who would forgive his sin or would take (him) to account for the sin. He again committed a sin and said: My Lord, forgive me for my sin, and Allah (the Exalted and High) said: My servant sas committed a sin and then came to realise that he has a Lord Who forgives the sins or takes (him) to account for sin. O servant, do what you like. I have granted you forgiveness. 'Abd al-A'la said: I do not know whether he said thrice or four times to do" what you desire" | E97: حَدَّثَنِي عَبْدُ الأَعْلَى بْنُ حَمَّادٍ، حَدَّثَنَا حَمَّادُ بْنُ سَلَمَةَ، عَنْ إِسْحَاقَ بْنِ عَبْدِ اللَّهِ، بْنِ أَبِي طَلْحَةَ عَنْ عَبْدِ الرَّحْمَنِ بْنِ أَبِي عَمْرَةَ، عَنْ أَبِي هُرَيْرَةَ، عَنِ النَّبِيِّ صلى الله عليه وسلم فِيمَا يَحْكِي عَنْ رَبِّهِ عَزَّ وَجَلَّ قَالَ ‏"‏ أَذْنَبَ عَبْدٌ ذَنْبًا فَقَالَ اللَّهُمَّ اغْفِرْ لِي ذَنْبِي ‏.‏ فَقَالَ تَبَارَكَ وَتَعَالَى أَذْنَبَ عَبْدِي ذَنْبًا فَعَلِمَ أَنَّ لَهُ رَبًّا يَغْفِرُ الذَّنْبَ وَيَأْخُذُ بِالذَّنْبِ ‏.‏ ثُمَّ عَادَ فَأَذْنَبَ فَقَالَ أَىْ رَبِّ اغْفِرْ لِي ذَنْبِي ‏.‏ فَقَالَ تَبَارَكَ وَتَعَالَى عَبْدِي أَذْنَبَ ذَنْبًا فَعَلِمَ أَنَّ لَهُ رَبًّا يَغْفِرُ الذَّنْبَ وَيَأْخُذُ بِالذَّنْبِ ‏.‏ ثُمَّ عَادَ فَأَذْنَبَ فَقَالَ أَىْ رَبِّ اغْفِرْ لِي ذَنْبِي ‏.‏ فَقَالَ تَبَارَكَ وَتَعَالَى أَذْنَبَ عَبْدِي ذَنْبًا فَعَلِمَ أَنَّ لَهُ رَبًّا يَغْفِرُ الذَّنْبَ وَيَأْخُذُ بِالذَّنْبِ وَاعْمَلْ مَا شِئْتَ فَقَدْ غَفَرْتُ لَكَ ‏"‏ ‏.‏ قَالَ عَبْدُ الأَعْلَى لاَ أَدْرِي أَقَالَ فِي الثَّالِثَةِ أَوِ الرَّابِعَةِ ‏"‏ اعْمَلْ مَا شِئْتَ ‏"‏ ‏.‏ | F97: Sahih Muslim 2758a | G97: Book 50, Hadith 33 | H97: Sahih | I97: https://sunnah.com/muslim:2758a
A98: 97 | B98: Repentance & forgiveness of sins | C98: Narrated Abu Hurairah:that the Messenger of Allah (ﷺ) said: "Do you think that if there was a river by the gate of one of you, and he bathed in it five times each day that there would remain any filth on him?" They said: "No filth would stay on him." He said: "That is the parable of the five prayers, Allah wipes out the sins with them" | E98: حَدَّثَنَا قُتَيْبَةُ، قَالَ‏ حَدَّثَنَا اللَّيْثُ، عَنِ ابْنِ الْهَادِ، عَنْ مُحَمَّدِ بْنِ إِبْرَاهِيمَ، عَنْ أَبِي سَلَمَةَ بْنِ عَبْدِ الرَّحْمَنِ، عَنْ أَبِي هُرَيْرَةَ، أَنَّ رَسُولَ اللَّهِ صلى الله عليه وسلم قَالَ ‏"‏ أَرَأَيْتُمْ لَوْ أَنَّ نَهْرًا بِبَابِ أَحَدِكُمْ يَغْتَسِلُ مِنْهُ كُلَّ يَوْمٍ خَمْسَ مَرَّاتٍ هَلْ يَبْقَى مِنْ دَرَنِهِ شَيْءٌ ‏"‏ ‏.‏ قَالُوا لاَ يَبْقَى مِنْ دَرَنِهِ شَيْءٌ ‏.‏ قَالَ ‏"‏ فَذَلِكَ مَثَلُ الصَّلَوَاتِ الْخَمْسِ يَمْحُو اللَّهُ بِهِنَّ الْخَطَايَا ‏"‏ ‏.‏ وَفِي الْبَابِ عَنْ جَابِرٍ ‏.‏ قَالَ أَبُو عِيسَى هَذَا حَدِيثٌ حَسَنٌ صَحِيحٌ ‏.‏ | F98: Jami' at-Tirmidhi 2868 | G98: Book 44, Hadith 10 | H98: Sahih (Al-Albani) | I98: https://sunnah.com/tirmidhi:2868
A99: 98 | B99: Repentance & forgiveness of sins | C99: The Messenger of Allah (ﷺ) said: “Whoever sits in a sitting and engages in much empty, meaningless speech and then says before getting from that sitting of his: ‘Glory is to You, O Allah, and praise, I bear witness that there is none worthy of worship except You, I seek You forgiveness, and I repent to You, (Subḥānaka Allāhumma wa biḥamdika, ashhadu an lā ilāha illā anta, astaghfiruka wa atūbu ilaik)’ whatever occurred in that sitting would be forgiven to him.” | D99: Abu Hurairah narrated that | E99: حَدَّثَنَا أَبُو عُبَيْدَةَ بْنُ أَبِي السَّفَرِ الْكُوفِيُّ، - وَاسْمُهُ أَحْمَدُ بْنُ عَبْدِ اللَّهِ الْهَمْدَانِيُّ حَدَّثَنَا حَجَّاجُ بْنُ مُحَمَّدٍ، قَالَ قَالَ ابْنُ جُرَيْجٍ أَخْبَرَنِي مُوسَى بْنُ عُقْبَةَ، عَنْ سُهَيْلِ بْنِ أَبِي صَالِحٍ، عَنْ أَبِيهِ، عَنْ أَبِي هُرَيْرَةَ، قَالَ قَالَ رَسُولُ اللَّهِ صلى الله عليه وسلم ‏ "‏ مَنْ جَلَسَ فِي مَجْلِسٍ فَكَثُرَ فِيهِ لَغَطُهُ فَقَالَ قَبْلَ أَنْ يَقُومَ مِنْ مَجْلِسِهِ ذَلِكَ سُبْحَانَكَ اللَّهُمَّ وَبِحَمْدِكَ أَشْهَدُ أَنْ لاَ إِلَهَ إِلاَّ أَنْتَ أَسْتَغْفِرُكَ وَأَتُوبُ إِلَيْكَ ‏.‏ إِلاَّ غُفِرَ لَهُ مَا كَانَ فِي مَجْلِسِهِ ذَلِكَ ‏"‏ ‏.‏ وَفِي الْبَابِ عَنْ أَبِي بَرْزَةَ وَعَائِشَةَ ‏.‏ قَالَ هَذَا حَدِيثٌ حَسَنٌ غَرِيبٌ صَحِيحٌ مِنْ هَذَا الْوَجْهِ لاَ نَعْرِفُهُ مِنْ حَدِيثِ سُهَيْلٍ إِلاَّ مِنْ هَذَا الْوَجْهِ ‏.‏ | F99: Jami' at-Tirmidhi 3433 | G99: Book 48, Hadith 64 | H99: Sahih (Al-Albani) | I99: https://sunnah.com/tirmidhi:3433
A100: 99 | B100: Repentance & forgiveness of sins | C100: The Messenger of Allah said to me: 'Have Taqwa of Allah wherever you are, and follow an evil deed with a good one to wipe it out, and treat the people with good behavior. | D100: Abu Dharr said | E100: حَدَّثَنَا مُحَمَّدُ بْنُ بَشَّارٍ، حَدَّثَنَا عَبْدُ الرَّحْمَنِ بْنُ مَهْدِيٍّ، حَدَّثَنَا سُفْيَانُ، عَنْ حَبِيبِ بْنِ أَبِي ثَابِتٍ، عَنْ مَيْمُونِ بْنِ أَبِي شَبِيبٍ، عَنْ أَبِي ذَرٍّ، قَالَ قَالَ لِي رَسُولُ اللَّهِ صلى الله عليه وسلم ‏ "‏ اتَّقِ اللَّهَ حَيْثُمَا كُنْتَ وَأَتْبِعِ السَّيِّئَةَ الْحَسَنَةَ تَمْحُهَا وَخَالِقِ النَّاسَ بِخُلُقٍ حَسَنٍ ‏"‏ ‏.‏ قَالَ وَفِي الْبَابِ عَنْ أَبِي هُرَيْرَةَ ‏.‏ قَالَ أَبُو عِيسَى هَذَا حَدِيثٌ حَسَنٌ صَحِيحٌ ‏.‏ حَدَّثَنَا مَحْمُودُ بْنُ غَيْلاَنَ، حَدَّثَنَا أَبُو أَحْمَدَ، وَأَبُو نُعَيْمٍ عَنْ سُفْيَانَ، عَنْ حَبِيبٍ، بِهَذَا الإِسْنَادِ نَحْوَهُ ‏.‏ قَالَ مَحْمُودٌ حَدَّثَنَا وَكِيعٌ، عَنْ سُفْيَانَ، عَنْ حَبِيبِ بْنِ أَبِي ثَابِتٍ، عَنْ مَيْمُونِ بْنِ أَبِي شَبِيبٍ، عَنْ مُعَاذِ بْنِ جَبَلٍ، عَنِ النَّبِيِّ صلى الله عليه وسلم نَحْوَهُ ‏.‏ قَالَ مَحْمُودٌ وَالصَّحِيحُ حَدِيثُ أَبِي ذَرٍّ ‏.‏ | F100: Jami' at-Tirmidhi 1987 | G100: Book 27, Hadith 93 | H100: Hasan (Al-Albani) | I100: https://sunnah.com/tirmidhi:1987
A101: 100 | B101: Repentance & forgiveness of sins | C101: We counted that the Messenger of Allah (ﷺ) would say a hundred times during a meeting: "My Lord, forgive me and pardon me; Thou art the Pardoning and forgiving One" | D101: Narrated Abdullah ibn Umar | E101: حَدَّثَنَا الْحَسَنُ بْنُ عَلِيٍّ، حَدَّثَنَا أَبُو أُسَامَةَ، عَنْ مَالِكِ بْنِ مِغْوَلٍ، عَنْ مُحَمَّدِ بْنِ سُوقَةَ، عَنْ نَافِعٍ، عَنِ ابْنِ عُمَرَ، قَالَ إِنْ كُنَّا لَنَعُدُّ لِرَسُولِ اللَّهِ صلى الله عليه وسلم فِي الْمَجْلِسِ الْوَاحِدِ مِائَةَ مَرَّةٍ ‏ "‏ رَبِّ اغْفِرْ لِي وَتُبْ عَلَىَّ إِنَّكَ أَنْتَ التَّوَّابُ الرَّحِيمُ ‏"‏ ‏.‏ | F101: Sunan Abi Dawud 1516 | G101: Book 8, Hadith 101 | H101: Sahih (Al-Albani) | I101: https://sunnah.com/abudawud:1516
A102: 101 | B102: Repentance & forgiveness of sins | C102: When the Prophet (ﷺ) uttered salutation at the end of the prayer, he used to say: "O Allah, forgive me my former and latter sins, what I have kept secret and what I have done openly, and what I have done extravagance; and what You know better than I do. You are the Advancer, the Delayer, there is no god but You" | D102: Ali b. Abi Talib said | E102: حَدَّثَنَا عُبَيْدُ اللَّهِ بْنُ مُعَاذٍ، قَالَ حَدَّثَنَا أَبِي، حَدَّثَنَا عَبْدُ الْعَزِيزِ بْنُ أَبِي سَلَمَةَ، عَنْ عَمِّهِ الْمَاجِشُونَ بْنِ أَبِي سَلَمَةَ، عَنْ عَبْدِ الرَّحْمَنِ الأَعْرَجِ، عَنْ عُبَيْدِ اللَّهِ بْنِ أَبِي رَافِعٍ، عَنْ عَلِيِّ بْنِ أَبِي طَالِبٍ، قَالَ كَانَ النَّبِيُّ صلى الله عليه وسلم إِذَا سَلَّمَ مِنَ الصَّلاَةِ قَالَ ‏ "‏ اللَّهُمَّ اغْفِرْ لِي مَا قَدَّمْتُ وَمَا أَخَّرْتُ وَمَا أَسْرَرْتُ وَمَا أَعْلَنْتُ وَمَا أَسْرَفْتُ وَمَا أَنْتَ أَعْلَمُ بِهِ مِنِّي أَنْتَ الْمُقَدِّمُ وَأَنْتَ الْمُؤَخِّرُ لاَ إِلَهَ إِلاَّ أَنْتَ ‏"‏ ‏.‏ | F102: Sunan Abi Dawud 1509 | G102: Book 8, Hadith 94 | H102: Sahih (Al-Albani) | I102: https://sunnah.com/abudawud:1509
A103: 102 | B103: Repentance & forgiveness of sins | C103: Abdullah bin Busr said that :the Prophet (saas) said: "Glad tidings to those who find a lot of seeking forgiveness in the record of their deeds" | E103: حَدَّثَنَا عَمْرُو بْنُ عُثْمَانَ بْنِ سَعِيدِ بْنِ كَثِيرِ بْنِ دِينَارٍ الْحِمْصِيُّ، حَدَّثَنَا أَبِي، حَدَّثَنَا مُحَمَّدُ بْنُ عَبْدِ الرَّحْمَنِ بْنِ عِرْقٍ، سَمِعْتُ عَبْدَ اللَّهِ بْنَ بُسْرٍ، يَقُولُ قَالَ النَّبِيُّ ـ صلى الله عليه وسلم ـ ‏ "‏ طُوبَى لِمَنْ وَجَدَ فِي صَحِيفَتِهِ اسْتِغْفَارًا كَثِيرًا ‏"‏ ‏.‏ | F103: Sunan Ibn Majah 3818 | G103: Book 33, Hadith 162 | H103: Sahih (Al-Albani) | I103: https://sunnah.com/ibnmajah:3818
A104: 103 | B104: Repentance & forgiveness of sins | C104: “The Messenger of Allah (ﷺ) said to me: ‘O ‘Aishah, beware of (evil) deeds that are regarded as insignificant, for they have a pursuer from Allah. (i.e. accountability).” | D104: It was narrated that ‘Aishah said | E104: حَدَّثَنَا أَبُو بَكْرِ بْنُ أَبِي شَيْبَةَ، حَدَّثَنَا خَالِدُ بْنُ مَخْلَدٍ، حَدَّثَنِي سَعِيدُ بْنُ مُسْلِمِ بْنِ بَانَكَ، قَالَ سَمِعْتُ عَامِرَ بْنَ عَبْدِ اللَّهِ بْنِ الزُّبَيْرِ، يَقُولُ ‏:‏ حَدَّثَنِي عَوْفُ بْنُ الْحَارِثِ، عَنْ عَائِشَةَ، قَالَتْ قَالَ لِي رَسُولُ اللَّهِ ـ صلى الله عليه وسلم ـ ‏:‏ ‏ "‏ يَا عَائِشَةُ إِيَّاكِ وَمُحَقَّرَاتِ الأَعْمَالِ فَإِنَّ لَهَا مِنَ اللَّهِ طَالِبًا ‏"‏ ‏.‏ | F104: Sunan Ibn Majah 4243 | G104: Book 37, Hadith 144 | H104: Sahih (Al-Albani) | I104: https://sunnah.com/ibnmajah:4243
A105: 104 | B105: Repentance & forgiveness of sins | C105: “If you were to commit sin until your sins reach the heaven, then you were to repent, your repentance would be accepted.” | D105: It was narrated from Abu Hurairah that the Prophet (ﷺ) said | E105: حَدَّثَنَا يَعْقُوبُ بْنُ حُمَيْدِ بْنِ كَاسِبٍ الْمَدَنِيُّ، حَدَّثَنَا أَبُو مُعَاوِيَةَ، حَدَّثَنَا جَعْفَرُ بْنُ بُرْقَانَ، عَنْ يَزِيدَ بْنِ الأَصَمِّ، عَنْ أَبِي هُرَيْرَةَ، عَنِ النَّبِيِّ ـ صلى الله عليه وسلم ـ قَالَ ‏:‏ ‏ "‏ لَوْ أَخْطَأْتُمْ حَتَّى تَبْلُغَ خَطَايَاكُمُ السَّمَاءَ ثُمَّ تُبْتُمْ لَتَابَ عَلَيْكُمْ ‏"‏ ‏.‏ | F105: Sunan Ibn Majah 4248 | G105: Book 37, Hadith 149 | H105: Hasan Sahih (Al-Albani) | I105: https://sunnah.com/ibnmajah:4248
A106: 105 | B106: Repentance & forgiveness of sins | C106: “I entered with my father upon ‘Abdullah, and I heard him say: ‘The messenger of Allah (ﷺ) said: “Regret is repentance.” My father said: ‘Did you hear the Prophet (ﷺ) say: “Regret is repentance?” He said: ‘Yes.’” | D106: It was narrated that Ibn Ma’qil said | E106: حَدَّثَنَا هِشَامُ بْنُ عَمَّارٍ، حَدَّثَنَا سُفْيَانُ، عَنْ عَبْدِ الْكَرِيمِ الْجَزَرِيِّ، عَنْ زِيَادِ بْنِ أَبِي مَرْيَمَ، عَنِ ابْنِ مَعْقِلٍ، قَالَ ‏:‏ دَخَلْتُ مَعَ أَبِي عَلَى عَبْدِ اللَّهِ فَسَمِعْتُهُ يَقُولُ قَالَ رَسُولُ اللَّهِ ـ صلى الله عليه وسلم ـ ‏:‏ ‏"‏ النَّدَمُ تَوْبَةٌ ‏"‏ ‏.‏ فَقَالَ لَهُ أَبِي ‏:‏ أَنْتَ سَمِعْتَ النَّبِيَّ ـ صلى الله عليه وسلم ـ يَقُولُ ‏:‏ ‏"‏ النَّدَمُ تَوْبَةٌ ‏"‏ ‏.‏ قَالَ ‏:‏ نَعَمْ ‏.‏ | F106: Sunan Ibn Majah 4252 | G106: Book 37, Hadith 153 | H106: Sahih (Al-Albani) | I106: https://sunnah.com/ibnmajah:4252
A107: 106 | B107: Repentance & forgiveness of sins | C107: “Allah accepts the repentance of His slave so long as the death rattle has not yet reached his throat.” | D107: It was narrated from ‘Abdullah bin ‘Amr that the Prophet (ﷺ) said | E107: حَدَّثَنَا رَاشِدُ بْنُ سَعِيدٍ الرَّمْلِيُّ، أَنْبَأَنَا الْوَلِيدُ بْنُ مُسْلِمٍ، عَنِ ابْنِ ثَوْبَانَ، عَنْ أَبِيهِ، عَنْ مَكْحُولٍ، عَنْ جُبَيْرِ بْنِ نُفَيْرٍ، عَنْ عَبْدِ اللَّهِ بْنِ عَمْرٍو، عَنِ النَّبِيِّ ـ صلى الله عليه وسلم ـ قَالَ ‏:‏ ‏ "‏ إِنَّ اللَّهَ عَزَّ وَجَلَّ لَيَقْبَلُ تَوْبَةَ الْعَبْدِ مَا لَمْ يُغَرْغِرْ ‏"‏ ‏.‏ | F107: Sunan Ibn Majah 4253 | G107: Book 37, Hadith 154 | H107: Hasan (Al-Albani) | I107: https://sunnah.com/ibnmajah:4253
A108: 107 | B108: Trust in Allah & destiny | C108: 'Allah is Sufficient for us and He Is the Best Disposer of affairs," was said by Abraham when he was thrown into the fire; and it was said by Muhammad when they (i.e. hypocrites) said, "A great army is gathering against you, therefore, fear them," but it only increased their faith and they said: "Allah is Sufficient for us, and He is the Best Disposer (of affairs, for us) | D108: Narrated Ibn `Abbas | E108: حَدَّثَنَا أَحْمَدُ بْنُ يُونُسَ ـ أُرَاهُ قَالَ ـ حَدَّثَنَا أَبُو بَكْرٍ، عَنْ أَبِي حَصِينٍ، عَنْ أَبِي الضُّحَى، عَنِ ابْنِ عَبَّاسٍ، ‏{‏حَسْبُنَا اللَّهُ وَنِعْمَ الْوَكِيلُ‏}‏ قَالَهَا إِبْرَاهِيمُ عَلَيْهِ السَّلاَمُ حِينَ أُلْقِيَ فِي النَّارِ، وَقَالَهَا مُحَمَّدٌ صلى الله عليه وسلم حِينَ قَالُوا ‏{‏إِنَّ النَّاسَ قَدْ جَمَعُوا لَكُمْ فَاخْشَوْهُمْ فَزَادَهُمْ إِيمَانًا وَقَالُوا حَسْبُنَا اللَّهُ وَنِعْمَ الْوَكِيلُ‏}‏ | F108: Sahih al-Bukhari 4563 | G108: Book 65, Hadith 85 | H108: Sahih | I108: https://sunnah.com/bukhari:4563
...

Sheet Topics
A1: Topic | B1: Count
A2: Patience in trials & hardship | B2: =COUNTIF(Hadith!B:B,A2) -> 16
A3: Illness & pain | B3: =COUNTIF(Hadith!B:B,A3) -> 17
A4: Grief, loss & death of loved ones | B4: =COUNTIF(Hadith!B:B,A4) -> 16
A5: Worry, anxiety & distress | B5: =COUNTIF(Hadith!B:B,A5) -> 12
A6: Hope in Allah's mercy | B6: =COUNTIF(Hadith!B:B,A6) -> 24
A7: Repentance & forgiveness of sins | B7: =COUNTIF(Hadith!B:B,A7) -> 21
A8: Trust in Allah & destiny | B8: =COUNTIF(Hadith!B:B,A8) -> 11
A9: Duas for difficult times | B9: =COUNTIF(Hadith!B:B,A9) -> 34
A10: Remembrance of Allah & peace of heart | B10: =COUNTIF(Hadith!B:B,A10) -> 32
A11: Gratitude | B11: =COUNTIF(Hadith!B:B,A11) -> 15
A12: Provision, poverty & contentment | B12: =COUNTIF(Hadith!B:B,A12) -> 19
A13: Debt & financial worries | B13: =COUNTIF(Hadith!B:B,A13) -> 10
... A28: This world & the hereafter | B28: =COUNTIF(Hadith!B:B,A28) -> 17
A29: Total | B29: =SUM(B2:B28) -> 500
A31: By collection | B31: Count
A32: Sahih al-Bukhari | B32: =COUNTIF(Hadith!F:F,"Sahih al-Bukhari *") -> 219
A33: Sahih Muslim | B33: =COUNTIF(Hadith!F:F,"Sahih Muslim *") -> 107
A34: Jami' at-Tirmidhi | B34: =COUNTIF(Hadith!F:F,"Jami' at-Tirmidhi *") -> 82
A35: Sunan Ibn Majah | B35: =COUNTIF(Hadith!F:F,"Sunan Ibn Majah *") -> 42
A36: Sunan an-Nasa'i | B36: =COUNTIF(Hadith!F:F,"Sunan an-Nasa'i *") -> 6
A37: Sunan Abi Dawud | B37: =COUNTIF(Hadith!F:F,"Sunan Abi Dawud *") -> 44

Sheet About
A1: 500 hadith on daily-life issues and consolation, grouped into 27 topics.
A2: Sources: Sahih al-Bukhari and Sahih Muslim (all), plus Jami' at-Tirmidhi, Sunan Abi Dawud, Sunan Ibn Majah and Sunan an-Nasa'i — only narrations Shaykh al-Albani graded Sahih or Hasan, with no other listed grader calling them weak; Companion statements (mawquf) excluded.
A3: Reference numbers follow sunnah.com (Muslim uses the Fu'ad 'Abd al-Baqi numbering, e.g. 2999, with a/b letters for variants). The Link column opens each hadith.
A4: English translations are the standard sunnah.com translations, taken from the open hadith-api dataset (github.com/fawazahmed0/hadith-api). Arabic text includes the full chain of narrators.
A5: Riyad as-Salihin (Imam an-Nawawi) was used to prioritise narrations scholars already collected for everyday conduct.
A6: Topic labels are an editorial grouping for browsing; some hadith fit several topics.
A7: Before publishing in an app, have a qualified scholar review the selection and topic assignments.
